[
  {
    "ID": 1,
    "Luogo": "Via Emilio Zago",
    "Emozione": "Felicità",
    "Fascia_eta": "18-25",
    "Sesso": "Donna",
    "Occupazione": "Studente/ssa",
    "Anni_Bologna": "Ci vivo da più di 5 anni",
    "Dove_cresciuto": "Altra città (o provincia) in Italia",
    "Quartiere_Bologna": "Bolognina",
    "Titolo_studio": "Laurea triennale",
    "Commento": "Ho iniziato a stare con il mio ragazzo"
  },
  {
    "ID": 2,
    "Luogo": "Via Creti",
    "Emozione": "Tristezza",
    "Fascia_eta": "18-25",
    "Sesso": "Donna",
    "Occupazione": "Studente/ssa",
    "Anni_Bologna": "Ci vivo da più di 5 anni",
    "Dove_cresciuto": "Altra città (o provincia) in Italia",
    "Quartiere_Bologna": "Bolognina",
    "Titolo_studio": "Laurea triennale",
    "Commento": "Ho litigato con il mio ragazzo"
  },
  {
    "ID": 3,
    "Luogo": "Via Stalingrado",
    "Emozione": "Disagio",
    "Fascia_eta": "18-25",
    "Sesso": "Donna",
    "Occupazione": "Studente/ssa",
    "Anni_Bologna": "Ci vivo da più di 5 anni",
    "Dove_cresciuto": "Altra città (o provincia) in Italia",
    "Quartiere_Bologna": "Bolognina",
    "Titolo_studio": "Laurea triennale",
    "Commento": "Quando tornavo a casa da sola la sera"
  },
  {
    "ID": 4,
    "Luogo": "Via Zago",
    "Emozione": "Accettazione",
    "Fascia_eta": "18-25",
    "Sesso": "Donna",
    "Occupazione": "Studente/ssa",
    "Anni_Bologna": "Ci vivo da più di 5 anni",
    "Dove_cresciuto": "Altra città (o provincia) in Italia",
    "Quartiere_Bologna": "Bolognina",
    "Titolo_studio": "Laurea triennale",
    "Commento": "Casa di mia sorella"
  },
  {
    "ID": 5,
    "Luogo": "Studentato Carducci",
    "Emozione": "Cambiamento",
    "Fascia_eta": "18-25",
    "Sesso": "Donna",
    "Occupazione": "Studente/ssa",
    "Anni_Bologna": "Ci vivo da più di 5 anni",
    "Dove_cresciuto": "Altra città (o provincia) in Italia",
    "Quartiere_Bologna": "Bolognina",
    "Titolo_studio": "Laurea triennale",
    "Commento": "È cambiata la mia vita"
  },
  {
    "ID": 6,
    "Luogo": "Giardino Del Guasto",
    "Emozione": "Felicità",
    "Fascia_eta": "18-25",
    "Sesso": "Donna",
    "Occupazione": "Studente/ssa",
    "Anni_Bologna": "Sono studente/ssa fuori sede",
    "Dove_cresciuto": "Altra città (o provincia) in Italia",
    "Quartiere_Bologna": "Bolognina",
    "Titolo_studio": "Diploma di scuola superiore",
    "Commento": "Ci andavo spesso per studiare e rilassarmi 2023-2025"
  },
  {
    "ID": 7,
    "Luogo": "Casteldebole",
    "Emozione": "Tristezza",
    "Fascia_eta": "18-25",
    "Sesso": "Donna",
    "Occupazione": "Studente/ssa",
    "Anni_Bologna": "Sono studente/ssa fuori sede",
    "Dove_cresciuto": "Altra città (o provincia) in Italia",
    "Quartiere_Bologna": "Bolognina",
    "Titolo_studio": "Diploma di scuola superiore",
    "Commento": "Mi ero appena trasferita a Bologna e c'era l'isolamento dal centro"
  },
  {
    "ID": 8,
    "Luogo": "Casteldebole",
    "Emozione": "Disagio",
    "Fascia_eta": "18-25",
    "Sesso": "Donna",
    "Occupazione": "Studente/ssa",
    "Anni_Bologna": "Sono studente/ssa fuori sede",
    "Dove_cresciuto": "Altra città (o provincia) in Italia",
    "Quartiere_Bologna": "Bolognina",
    "Titolo_studio": "Diploma di scuola superiore",
    "Commento": "Non mi sentivo a casa ogni volta che mi trovavo lì"
  },
  {
    "ID": 9,
    "Luogo": "Via Mascarella",
    "Emozione": "Accettazione",
    "Fascia_eta": "18-25",
    "Sesso": "Donna",
    "Occupazione": "Studente/ssa",
    "Anni_Bologna": "Sono studente/ssa fuori sede",
    "Dove_cresciuto": "Altra città (o provincia) in Italia",
    "Quartiere_Bologna": "Bolognina",
    "Titolo_studio": "Diploma di scuola superiore",
    "Commento": "I miei familiari ed i miei studi, le partenze per casa o i ritorni"
  },
  {
    "ID": 10,
    "Luogo": "Zona San Donato",
    "Emozione": "Cambiamento",
    "Fascia_eta": "18-25",
    "Sesso": "Donna",
    "Occupazione": "Studente/ssa",
    "Anni_Bologna": "Sono studente/ssa fuori sede",
    "Dove_cresciuto": "Altra città (o provincia) in Italia",
    "Quartiere_Bologna": "Bolognina",
    "Titolo_studio": "Diploma di scuola superiore",
    "Commento": "Entrambe le cose"
  },
  {
    "ID": 11,
    "Luogo": "Piazza Aldrovandi",
    "Emozione": "Felicità",
    "Fascia_eta": "18-25",
    "Sesso": "Donna",
    "Occupazione": "Altro",
    "Anni_Bologna": "Sono studente/ssa fuori sede",
    "Dove_cresciuto": "Altra città (o provincia) in Emilia Romagna",
    "Quartiere_Bologna": "Lame",
    "Titolo_studio": "Laurea triennale",
    "Commento": "Nei miei primi anni universitari (ormai 3/4 anni fa) passavo spesso le serate lì con i miei gruppi di amici e amiche. Senza fare nulla di speciale, stavamo seduti in piazza o stavamo in piedi a chiacchierare, ridere e condividere momenti, anche con qualche birretta o drink"
  },
  {
    "ID": 12,
    "Luogo": "Bolognina",
    "Emozione": "Tristezza",
    "Fascia_eta": "18-25",
    "Sesso": "Donna",
    "Occupazione": "Altro",
    "Anni_Bologna": "Sono studente/ssa fuori sede",
    "Dove_cresciuto": "Altra città (o provincia) in Emilia Romagna",
    "Quartiere_Bologna": "Lame",
    "Titolo_studio": "Laurea triennale",
    "Commento": "In realtà l'ho superata, ma in un determinato periodo, ogni volta che passavo in quelle zone sentivo una forte tristezza e vuoto interiore. Questo perché avevo chiuso con il mio ragazzo e con il gruppo di amici a lui annesso e con cui uscivamo. Abbiamo passato tanti momenti divertenti nel quartiere."
  },
  {
    "ID": 13,
    "Luogo": "Bologna Centro",
    "Emozione": "Accettazione",
    "Fascia_eta": "18-25",
    "Sesso": "Donna",
    "Occupazione": "Altro",
    "Anni_Bologna": "Sono studente/ssa fuori sede",
    "Dove_cresciuto": "Altra città (o provincia) in Emilia Romagna",
    "Quartiere_Bologna": "Lame",
    "Titolo_studio": "Laurea triennale",
    "Commento": "Mi sento in questo modo poiché nella mia cittadina mi sono sempre sentita in imbarazzo ad uscire ad esempio con una tuta, con delle ciabatte o con i capelli fuori posto o leggermente sporchi. Bologna essendo più grande, nessuno fa caso a te e come sei vestito, per cui mi sento maggiormente a mio agio ovunque in città"
  },
  {
    "ID": 14,
    "Luogo": "Bologna Centro",
    "Emozione": "Cambiamento",
    "Fascia_eta": "18-25",
    "Sesso": "Donna",
    "Occupazione": "Altro",
    "Anni_Bologna": "Sono studente/ssa fuori sede",
    "Dove_cresciuto": "Altra città (o provincia) in Emilia Romagna",
    "Quartiere_Bologna": "Lame",
    "Titolo_studio": "Laurea triennale",
    "Commento": "Il luogo e anche io sicuramente sono cresciuta e sono meno ingenua"
  },
  {
    "ID": 15,
    "Luogo": "Via Creti",
    "Emozione": "Felicità",
    "Fascia_eta": "26-35",
    "Sesso": "Uomo",
    "Occupazione": "Occupato autonomo (libero/a professionista, imprenditore/trice, artigiano/a)",
    "Anni_Bologna": "Ci vivo da più di 5 anni e non sono studente/ssa fuori sede",
    "Dove_cresciuto": "Altra città (o provincia) in Emilia Romagna",
    "Quartiere_Bologna": "Bolognina",
    "Titolo_studio": "Diploma di scuola superiore",
    "Commento": "Ho trovato la mia fidanzata"
  },
  {
    "ID": 16,
    "Luogo": "Chiesa Santi Monica e Agostino",
    "Emozione": "Felicità",
    "Fascia_eta": "36-45",
    "Sesso": "Donna",
    "Occupazione": "Disoccupato/a",
    "Anni_Bologna": "Ci vivo da più di 5 anni e non sono studente/ssa fuori sede",
    "Dove_cresciuto": "Altra città (o provincia) in Italia",
    "Quartiere_Bologna": "Corticella",
    "Titolo_studio": "Laurea magistrale o superiore",
    "Commento": "Il battesimo delle mie figlie"
  },
  {
    "ID": 17,
    "Luogo": "Bolognina",
    "Emozione": "Disagio",
    "Fascia_eta": "36-45",
    "Sesso": "Donna",
    "Occupazione": "Disoccupato/a",
    "Anni_Bologna": "Ci vivo da più di 5 anni e non sono studente/ssa fuori sede",
    "Dove_cresciuto": "Altra città (o provincia) in Italia",
    "Quartiere_Bologna": "Corticella",
    "Titolo_studio": "Laurea magistrale o superiore",
    "Commento": "Sì, scarsa sicurezza civica."
  },
  {
    "ID": 18,
    "Luogo": "Centro Civico e Villa Torchi",
    "Emozione": "Cambiamento",
    "Fascia_eta": "36-45",
    "Sesso": "Donna",
    "Occupazione": "Disoccupato/a",
    "Anni_Bologna": "Ci vivo da più di 5 anni e non sono studente/ssa fuori sede",
    "Dove_cresciuto": "Altra città (o provincia) in Italia",
    "Quartiere_Bologna": "Corticella",
    "Titolo_studio": "Laurea magistrale o superiore",
    "Commento": "Più delinquenza. È peggiorata la situazione"
  },
  {
    "ID": 19,
    "Luogo": "Ippodromo",
    "Emozione": "Felicità",
    "Fascia_eta": "56-65",
    "Sesso": "Donna",
    "Occupazione": "Occupato/a dipendente",
    "Anni_Bologna": "Sono nato/a e cresciuto/a qui",
    "Dove_cresciuto": "Bologna (o provincia)",
    "Quartiere_Bologna": "Bolognina",
    "Titolo_studio": "Laurea magistrale o superiore",
    "Commento": "Da piccola giocavo, pattinavo e andavo in bicicletta lì con i miei amici"
  },
  {
    "ID": 20,
    "Luogo": "Stazione Centrale",
    "Emozione": "Tristezza",
    "Fascia_eta": "56-65",
    "Sesso": "Donna",
    "Occupazione": "Occupato/a dipendente",
    "Anni_Bologna": "Sono nato/a e cresciuto/a qui",
    "Dove_cresciuto": "Bologna (o provincia)",
    "Quartiere_Bologna": "Bolognina",
    "Titolo_studio": "Laurea magistrale o superiore",
    "Commento": "Quando scoppiò la bomba della strage del 2 agosto ero un'adolescente che prendeva l'autobus n. 37 (quello che portò via le salme) proprio lì."
  },
  {
    "ID": 21,
    "Luogo": "Stazione Centrale",
    "Emozione": "Disagio",
    "Fascia_eta": "56-65",
    "Sesso": "Donna",
    "Occupazione": "Occupato/a dipendente",
    "Anni_Bologna": "Sono nato/a e cresciuto/a qui",
    "Dove_cresciuto": "Bologna (o provincia)",
    "Quartiere_Bologna": "Bolognina",
    "Titolo_studio": "Laurea magistrale o superiore",
    "Commento": "È un posto poco sicuro."
  },
  {
    "ID": 22,
    "Luogo": "Bolognina",
    "Emozione": "Accettazione",
    "Fascia_eta": "56-65",
    "Sesso": "Donna",
    "Occupazione": "Occupato/a dipendente",
    "Anni_Bologna": "Sono nato/a e cresciuto/a qui",
    "Dove_cresciuto": "Bologna (o provincia)",
    "Quartiere_Bologna": "Bolognina",
    "Titolo_studio": "Laurea magistrale o superiore",
    "Commento": "Ci sono nata e cresciuta"
  },
  {
    "ID": 23,
    "Luogo": "Bologna Centro",
    "Emozione": "Cambiamento",
    "Fascia_eta": "56-65",
    "Sesso": "Donna",
    "Occupazione": "Occupato/a dipendente",
    "Anni_Bologna": "Sono nato/a e cresciuto/a qui",
    "Dove_cresciuto": "Bologna (o provincia)",
    "Quartiere_Bologna": "Bolognina",
    "Titolo_studio": "Laurea magistrale o superiore",
    "Commento": "Entrambe le cose"
  },
  {
    "ID": 24,
    "Luogo": "Via Barbieri Dal n. 75 al n. 99",
    "Emozione": "Felicità",
    "Fascia_eta": "56-65",
    "Sesso": "Uomo",
    "Occupazione": "Occupato/a dipendente",
    "Anni_Bologna": "Sono nato/a e cresciuto/a qui",
    "Dove_cresciuto": "Bologna (o provincia)",
    "Quartiere_Bologna": "Bolognina",
    "Titolo_studio": "Laurea magistrale o superiore",
    "Commento": "In via Barbieri 99 abitavo lì con i miei genitori da piccolo e in via Barbieri n. 75 abitavano i miei nonni."
  },
  {
    "ID": 25,
    "Luogo": "Ospedale Maggiore",
    "Emozione": "Tristezza",
    "Fascia_eta": "56-65",
    "Sesso": "Uomo",
    "Occupazione": "Occupato/a dipendente",
    "Anni_Bologna": "Sono nato/a e cresciuto/a qui",
    "Dove_cresciuto": "Bologna (o provincia)",
    "Quartiere_Bologna": "Bolognina",
    "Titolo_studio": "Laurea magistrale o superiore",
    "Commento": "È morta mia mamma all'ospedale Maggiore"
  },
  {
    "ID": 26,
    "Luogo": "Fondo Comini",
    "Emozione": "Accettazione",
    "Fascia_eta": "56-65",
    "Sesso": "Uomo",
    "Occupazione": "Occupato/a dipendente",
    "Anni_Bologna": "Sono nato/a e cresciuto/a qui",
    "Dove_cresciuto": "Bologna (o provincia)",
    "Quartiere_Bologna": "Bolognina",
    "Titolo_studio": "Laurea magistrale o superiore",
    "Commento": "Da piccolo passavo interi pomeriggi a giocare a pallone."
  },
  {
    "ID": 27,
    "Luogo": "Ex Mercato Ortofrutticolo",
    "Emozione": "Cambiamento",
    "Fascia_eta": "56-65",
    "Sesso": "Uomo",
    "Occupazione": "Occupato/a dipendente",
    "Anni_Bologna": "Sono nato/a e cresciuto/a qui",
    "Dove_cresciuto": "Bologna (o provincia)",
    "Quartiere_Bologna": "Bolognina",
    "Titolo_studio": "Laurea magistrale o superiore",
    "Commento": "Il mercato non c'è più e ci sono palazzoni nuovi."
  },
  {
    "ID": 28,
    "Luogo": "Dopolavoro Ferroviario",
    "Emozione": "Felicità",
    "Fascia_eta": "Più di 65",
    "Sesso": "Donna",
    "Occupazione": "Pensionato/a",
    "Anni_Bologna": "Sono nato/a e cresciuto/a qui",
    "Dove_cresciuto": "Bologna (o provincia)",
    "Quartiere_Bologna": "Bolognina",
    "Titolo_studio": "Diploma di scuola superiore",
    "Commento": "Ci ho passato l'infanzia. In particolare ricordo quando andavo a guardare il gioco delle bocce con il nonno"
  },
  {
    "ID": 29,
    "Luogo": "Stazione Centrale",
    "Emozione": "Tristezza",
    "Fascia_eta": "Più di 65",
    "Sesso": "Donna",
    "Occupazione": "Pensionato/a",
    "Anni_Bologna": "Sono nato/a e cresciuto/a qui",
    "Dove_cresciuto": "Bologna (o provincia)",
    "Quartiere_Bologna": "Bolognina",
    "Titolo_studio": "Diploma di scuola superiore",
    "Commento": "Io non ero a Bologna. Ho sentito dell'attentato alla radio. Ricordo l'ansia per i miei, la difficoltà a telefonare, il panico. E poi, dopo, le immagini terribili alla televisione"
  },
  {
    "ID": 30,
    "Luogo": "Bologna Centro",
    "Emozione": "Disagio",
    "Fascia_eta": "Più di 65",
    "Sesso": "Donna",
    "Occupazione": "Pensionato/a",
    "Anni_Bologna": "Sono nato/a e cresciuto/a qui",
    "Dove_cresciuto": "Bologna (o provincia)",
    "Quartiere_Bologna": "Bolognina",
    "Titolo_studio": "Diploma di scuola superiore",
    "Commento": "Soprattutto nel weekend, la città non mi sembra più la stessa. Mi sento ancora a casa in Bolognina"
  },
  {
    "ID": 31,
    "Luogo": "Biblioteca Sala Borsa",
    "Emozione": "Accettazione",
    "Fascia_eta": "Più di 65",
    "Sesso": "Donna",
    "Occupazione": "Pensionato/a",
    "Anni_Bologna": "Sono nato/a e cresciuto/a qui",
    "Dove_cresciuto": "Bologna (o provincia)",
    "Quartiere_Bologna": "Bolognina",
    "Titolo_studio": "Diploma di scuola superiore",
    "Commento": "Il fatto che ho partecipato alla sua nascita"
  },
  {
    "ID": 32,
    "Luogo": "Bologna Centro",
    "Emozione": "Cambiamento",
    "Fascia_eta": "Più di 65",
    "Sesso": "Donna",
    "Occupazione": "Pensionato/a",
    "Anni_Bologna": "Sono nato/a e cresciuto/a qui",
    "Dove_cresciuto": "Bologna (o provincia)",
    "Quartiere_Bologna": "Bolognina",
    "Titolo_studio": "Diploma di scuola superiore",
    "Commento": "È cambiato il modo di intendere la città."
  },
  {
    "ID": 33,
    "Luogo": "Piazza Maggiore",
    "Emozione": "Felicità",
    "Fascia_eta": "Più di 65",
    "Sesso": "Donna",
    "Occupazione": "Pensionato/a",
    "Anni_Bologna": "Sono nato/a e cresciuto/a qui",
    "Dove_cresciuto": "Bologna (o provincia)",
    "Quartiere_Bologna": "Bolognina",
    "Titolo_studio": "Diploma di scuola superiore",
    "Commento": "Quando mi sono sposata"
  },
  {
    "ID": 34,
    "Luogo": "Casa di Lucio Dalla",
    "Emozione": "Tristezza",
    "Fascia_eta": "Più di 65",
    "Sesso": "Donna",
    "Occupazione": "Pensionato/a",
    "Anni_Bologna": "Sono nato/a e cresciuto/a qui",
    "Dove_cresciuto": "Bologna (o provincia)",
    "Quartiere_Bologna": "Bolognina",
    "Titolo_studio": "Diploma di scuola superiore",
    "Commento": "Passarci davanti e pensare che Lucio non c'è più."
  },
  {
    "ID": 35,
    "Luogo": "Parco della Montagnola",
    "Emozione": "Disagio",
    "Fascia_eta": "Più di 65",
    "Sesso": "Donna",
    "Occupazione": "Pensionato/a",
    "Anni_Bologna": "Sono nato/a e cresciuto/a qui",
    "Dove_cresciuto": "Bologna (o provincia)",
    "Quartiere_Bologna": "Bolognina",
    "Titolo_studio": "Diploma di scuola superiore",
    "Commento": "Sensazione di paura… passeggio"
  },
  {
    "ID": 36,
    "Luogo": "Bologna Centro",
    "Emozione": "Accettazione",
    "Fascia_eta": "Più di 65",
    "Sesso": "Donna",
    "Occupazione": "Pensionato/a",
    "Anni_Bologna": "Sono nato/a e cresciuto/a qui",
    "Dove_cresciuto": "Bologna (o provincia)",
    "Quartiere_Bologna": "Bolognina",
    "Titolo_studio": "Diploma di scuola superiore",
    "Commento": "Ti senti il vero bolognese passeggiando per la piazza"
  },
  {
    "ID": 37,
    "Luogo": "Bologna Centro",
    "Emozione": "Cambiamento",
    "Fascia_eta": "Più di 65",
    "Sesso": "Donna",
    "Occupazione": "Pensionato/a",
    "Anni_Bologna": "Sono nato/a e cresciuto/a qui",
    "Dove_cresciuto": "Bologna (o provincia)",
    "Quartiere_Bologna": "Bolognina",
    "Titolo_studio": "Diploma di scuola superiore",
    "Commento": "Le persone … o forse sono cambiata io"
  },
  {
    "ID": 38,
    "Luogo": "San Luca",
    "Emozione": "Felicità",
    "Fascia_eta": "26-35",
    "Sesso": "Donna",
    "Occupazione": "Occupato/a dipendente",
    "Anni_Bologna": "Ci vivo da più di 5 anni e non sono studente/ssa fuori sede",
    "Dove_cresciuto": "Altra città (o provincia) in Italia",
    "Quartiere_Bologna": "Lame",
    "Titolo_studio": "Laurea magistrale o superiore",
    "Commento": "Le mattine fredde invernali in cui salgo a San Luca e poi mangio due pizzette al Bar Billi"
  },
  {
    "ID": 39,
    "Luogo": "Villa Spada",
    "Emozione": "Tristezza",
    "Fascia_eta": "26-35",
    "Sesso": "Donna",
    "Occupazione": "Occupato/a dipendente",
    "Anni_Bologna": "Ci vivo da più di 5 anni e non sono studente/ssa fuori sede",
    "Dove_cresciuto": "Altra città (o provincia) in Italia",
    "Quartiere_Bologna": "Lame",
    "Titolo_studio": "Laurea magistrale o superiore",
    "Commento": "Mi sono sentita rifiutata e inadeguata, sono stata lasciata lì"
  },
  {
    "ID": 40,
    "Luogo": "Villaggio Del Fanciullo",
    "Emozione": "Accettazione",
    "Fascia_eta": "26-35",
    "Sesso": "Donna",
    "Occupazione": "Occupato/a dipendente",
    "Anni_Bologna": "Ci vivo da più di 5 anni e non sono studente/ssa fuori sede",
    "Dove_cresciuto": "Altra città (o provincia) in Italia",
    "Quartiere_Bologna": "Lame",
    "Titolo_studio": "Laurea magistrale o superiore",
    "Commento": "Faccio volontariato lì da 5 anni, lì sto molto bene con le persone con cui faccio servizio - vecchie e nuove compagnie ma sempre molto belle"
  },
  {
    "ID": 41,
    "Luogo": "Largo Respighi",
    "Emozione": "Cambiamento",
    "Fascia_eta": "26-35",
    "Sesso": "Donna",
    "Occupazione": "Occupato/a dipendente",
    "Anni_Bologna": "Ci vivo da più di 5 anni e non sono studente/ssa fuori sede",
    "Dove_cresciuto": "Altra città (o provincia) in Italia",
    "Quartiere_Bologna": "Lame",
    "Titolo_studio": "Laurea magistrale o superiore",
    "Commento": "Sono cresciuta, li associo al periodo universitario, in cui avevo più tempo di vivere la città. Adesso è tutta una corsa e mai una passeggiata tra le strade di Bologna"
  },
  {
    "ID": 42,
    "Luogo": "Via S. Felice 38/3",
    "Emozione": "Felicità",
    "Fascia_eta": "36-45",
    "Sesso": "Donna",
    "Occupazione": "Occupato/a dipendente",
    "Anni_Bologna": "Ci vivo da più di 5 anni e non sono studente/ssa fuori sede",
    "Dove_cresciuto": "Altra città (o provincia) in Italia",
    "Quartiere_Bologna": "Bolognina",
    "Titolo_studio": "Laurea magistrale o superiore",
    "Commento": "Una nuova vita, fatta di amici e coinquilini che a distanza di 20 anni ancora frequento"
  },
  {
    "ID": 43,
    "Luogo": "Parco della Montagnola",
    "Emozione": "Tristezza",
    "Fascia_eta": "36-45",
    "Sesso": "Donna",
    "Occupazione": "Occupato/a dipendente",
    "Anni_Bologna": "Ci vivo da più di 5 anni e non sono studente/ssa fuori sede",
    "Dove_cresciuto": "Altra città (o provincia) in Italia",
    "Quartiere_Bologna": "Bolognina",
    "Titolo_studio": "Laurea magistrale o superiore",
    "Commento": "Ho conosciuto una persona che mi ha perseguitata per quasi 3 anni"
  },
  {
    "ID": 44,
    "Luogo": "Ponte di Stalingrado",
    "Emozione": "Disagio",
    "Fascia_eta": "36-45",
    "Sesso": "Donna",
    "Occupazione": "Occupato/a dipendente",
    "Anni_Bologna": "Ci vivo da più di 5 anni e non sono studente/ssa fuori sede",
    "Dove_cresciuto": "Altra città (o provincia) in Italia",
    "Quartiere_Bologna": "Bolognina",
    "Titolo_studio": "Laurea magistrale o superiore",
    "Commento": "Era il mio primo anno a Bologna e dovevo vedere una casa che si trovava a pochi metri da questo tappeto di siringhe"
  },
  {
    "ID": 45,
    "Luogo": "Via Filippo Re",
    "Emozione": "Accettazione",
    "Fascia_eta": "36-45",
    "Sesso": "Donna",
    "Occupazione": "Occupato/a dipendente",
    "Anni_Bologna": "Ci vivo da più di 5 anni e non sono studente/ssa fuori sede",
    "Dove_cresciuto": "Altra città (o provincia) in Italia",
    "Quartiere_Bologna": "Bolognina",
    "Titolo_studio": "Laurea magistrale o superiore",
    "Commento": "Sono cresciuta interiormente, mi sono evoluta nell'università, scienze della formazione in"
  },
  {
    "ID": 46,
    "Luogo": "Via Zamboni",
    "Emozione": "Felicità",
    "Fascia_eta": "46-55",
    "Sesso": "Uomo",
    "Occupazione": "Disoccupato/a",
    "Anni_Bologna": "Ci vivo da più di 5 anni e non sono studente/ssa fuori sede",
    "Dove_cresciuto": "Altra città (o provincia) in Emilia Romagna",
    "Quartiere_Bologna": "Bolognina",
    "Titolo_studio": "Laurea magistrale o superiore",
    "Commento": "Dottorato di ricerca 2005"
  },
  {
    "ID": 47,
    "Luogo": "Via San Vitale",
    "Emozione": "Tristezza",
    "Fascia_eta": "46-55",
    "Sesso": "Uomo",
    "Occupazione": "Disoccupato/a",
    "Anni_Bologna": "Ci vivo da più di 5 anni e non sono studente/ssa fuori sede",
    "Dove_cresciuto": "Altra città (o provincia) in Emilia Romagna",
    "Quartiere_Bologna": "Bolognina",
    "Titolo_studio": "Laurea magistrale o superiore",
    "Commento": "Rifiuto amoroso"
  },
  {
    "ID": 48,
    "Luogo": "Via Del Pratello",
    "Emozione": "Disagio",
    "Fascia_eta": "46-55",
    "Sesso": "Uomo",
    "Occupazione": "Disoccupato/a",
    "Anni_Bologna": "Ci vivo da più di 5 anni e non sono studente/ssa fuori sede",
    "Dove_cresciuto": "Altra città (o provincia) in Emilia Romagna",
    "Quartiere_Bologna": "Bolognina",
    "Titolo_studio": "Laurea magistrale o superiore",
    "Commento": "Rumore, urla, tanta gente, spinte, dovevo andare in un locale, sono andato via"
  },
  {
    "ID": 49,
    "Luogo": "Via Zamboni",
    "Emozione": "Accettazione",
    "Fascia_eta": "46-55",
    "Sesso": "Uomo",
    "Occupazione": "Disoccupato/a",
    "Anni_Bologna": "Ci vivo da più di 5 anni e non sono studente/ssa fuori sede",
    "Dove_cresciuto": "Altra città (o provincia) in Emilia Romagna",
    "Quartiere_Bologna": "Bolognina",
    "Titolo_studio": "Laurea magistrale o superiore",
    "Commento": "Studiavo cose che mi piacevano"
  },
  {
    "ID": 50,
    "Luogo": "Giardini Margherita",
    "Emozione": "Felicità",
    "Fascia_eta": "46-55",
    "Sesso": "Donna",
    "Occupazione": "Occupato/a dipendente",
    "Anni_Bologna": "Sono nato/a e cresciuto/a qui",
    "Dove_cresciuto": "Bologna (o provincia)",
    "Quartiere_Bologna": "Corticella",
    "Titolo_studio": "Diploma di scuola superiore",
    "Commento": "Ho vissuto molti bei momenti con la mia migliore amica e il mio ragazzo di allora"
  },
  {
    "ID": 51,
    "Luogo": "Stazione Centrale",
    "Emozione": "Tristezza",
    "Fascia_eta": "46-55",
    "Sesso": "Donna",
    "Occupazione": "Occupato/a dipendente",
    "Anni_Bologna": "Sono nato/a e cresciuto/a qui",
    "Dove_cresciuto": "Bologna (o provincia)",
    "Quartiere_Bologna": "Corticella",
    "Titolo_studio": "Diploma di scuola superiore",
    "Commento": "La strage del 2/8/80"
  },
  {
    "ID": 52,
    "Luogo": "Parco della Montagnola",
    "Emozione": "Disagio",
    "Fascia_eta": "46-55",
    "Sesso": "Donna",
    "Occupazione": "Occupato/a dipendente",
    "Anni_Bologna": "Sono nato/a e cresciuto/a qui",
    "Dove_cresciuto": "Bologna (o provincia)",
    "Quartiere_Bologna": "Corticella",
    "Titolo_studio": "Diploma di scuola superiore",
    "Commento": "Negli anni 90 quando erano in stato di abbandono e frequentati solo da tossici e spacciatori. Era una sensazione di disagio e di poca sicurezza"
  },
  {
    "ID": 53,
    "Luogo": "Giardini Del Laghetto di Corticella",
    "Emozione": "Accettazione",
    "Fascia_eta": "46-55",
    "Sesso": "Donna",
    "Occupazione": "Occupato/a dipendente",
    "Anni_Bologna": "Sono nato/a e cresciuto/a qui",
    "Dove_cresciuto": "Bologna (o provincia)",
    "Quartiere_Bologna": "Corticella",
    "Titolo_studio": "Diploma di scuola superiore",
    "Commento": "Da quando lo hanno creato frequento questo luogo assiduamente, con le mie figlie piccole, ora con i miei genitori anziani o quando voglio stare sola per una bella passeggiata a passo veloce"
  },
  {
    "ID": 54,
    "Luogo": "Giardini Margherita",
    "Emozione": "Felicità",
    "Fascia_eta": "56-65",
    "Sesso": "Donna",
    "Occupazione": "Occupato autonomo (libero/a professionista, imprenditore/trice, artigiano/a)",
    "Anni_Bologna": "Ci vivo da più di 5 anni e non sono studente/ssa fuori sede",
    "Dove_cresciuto": "Altra città (o provincia) in Emilia Romagna",
    "Quartiere_Bologna": "Bolognina",
    "Titolo_studio": "Laurea magistrale o superiore",
    "Commento": "Le prime pause pranzo nel verde"
  },
  {
    "ID": 55,
    "Luogo": "Giardini Margherita",
    "Emozione": "Accettazione",
    "Fascia_eta": "56-65",
    "Sesso": "Donna",
    "Occupazione": "Occupato autonomo (libero/a professionista, imprenditore/trice, artigiano/a)",
    "Anni_Bologna": "Ci vivo da più di 5 anni e non sono studente/ssa fuori sede",
    "Dove_cresciuto": "Altra città (o provincia) in Emilia Romagna",
    "Quartiere_Bologna": "Bolognina",
    "Titolo_studio": "Laurea magistrale o superiore",
    "Commento": "Mi fanno sentire un po' più nelle campagne dove sono cresciuta"
  },
  {
    "ID": 56,
    "Luogo": "Bolognina",
    "Emozione": "Felicità",
    "Fascia_eta": "56-65",
    "Sesso": "Donna",
    "Occupazione": "Occupato autonomo (libero/a professionista, imprenditore/trice, artigiano/a)",
    "Anni_Bologna": "Sono nato/a e cresciuto/a qui",
    "Dove_cresciuto": "Bologna (o provincia)",
    "Quartiere_Bologna": "Bolognina",
    "Titolo_studio": "Diploma di scuola superiore",
    "Commento": "Ho trascorso tutta la mia infanzia giocando intere giornate con amiche e amici, momenti indimenticabili vissuti in tranquillità, senza preoccupazioni... eravamo tutti felici (con niente)"
  },
  {
    "ID": 57,
    "Luogo": "Bolognina",
    "Emozione": "Accettazione",
    "Fascia_eta": "56-65",
    "Sesso": "Donna",
    "Occupazione": "Occupato autonomo (libero/a professionista, imprenditore/trice, artigiano/a)",
    "Anni_Bologna": "Sono nato/a e cresciuto/a qui",
    "Dove_cresciuto": "Bologna (o provincia)",
    "Quartiere_Bologna": "Bolognina",
    "Titolo_studio": "Diploma di scuola superiore",
    "Commento": "Sono nata in Bolognina e sto vivendo lì ormai da quasi 60 anni. Seppur cambiato il mio quartiere negli ultimi tempi non lo cambierei con nessun altro al mondo. È tutto comodo e a portata di mano e posso raggiungere il centro a piedi"
  },
  {
    "ID": 58,
    "Luogo": "Bolognina",
    "Emozione": "Cambiamento",
    "Fascia_eta": "56-65",
    "Sesso": "Donna",
    "Occupazione": "Occupato autonomo (libero/a professionista, imprenditore/trice, artigiano/a)",
    "Anni_Bologna": "Sono nato/a e cresciuto/a qui",
    "Dove_cresciuto": "Bologna (o provincia)",
    "Quartiere_Bologna": "Bolognina",
    "Titolo_studio": "Diploma di scuola superiore",
    "Commento": "Il luogo è lo stesso bene o male, ma ci sono persone diverse, prima tutti bolognesi ora non più purtroppo"
  },
  {
    "ID": 59,
    "Luogo": "Piazza Verdi",
    "Emozione": "Felicità",
    "Fascia_eta": "26-35",
    "Sesso": "Donna",
    "Occupazione": "Studente/ssa",
    "Anni_Bologna": "Sono studente/ssa fuori sede",
    "Dove_cresciuto": "Altra città (o provincia) in Italia",
    "Quartiere_Bologna": "Bolognina",
    "Titolo_studio": "Laurea triennale",
    "Commento": "1) prima casa a Bologna 2) spazio verde molto amato 3) per il mercatino del Senza chiedere permesso e varie assemblee e presentazioni 4) aggiungo il parco davanti all'ex caserma Sani per le assemblee organizzate per fare una controproposta al comune in modo da rendere quello spazio pubblico e sociale anziché l'ennesimo parcheggio/centro commerciale"
  },
  {
    "ID": 60,
    "Luogo": "Piazza Verdi",
    "Emozione": "Tristezza",
    "Fascia_eta": "26-35",
    "Sesso": "Donna",
    "Occupazione": "Studente/ssa",
    "Anni_Bologna": "Sono studente/ssa fuori sede",
    "Dove_cresciuto": "Altra città (o provincia) in Italia",
    "Quartiere_Bologna": "Bolognina",
    "Titolo_studio": "Laurea triennale",
    "Commento": "Spaccio e consumo di droga, non ero spaventata ma dispiaciuta per tutte queste persone lasciate volutamente ai margini."
  },
  {
    "ID": 61,
    "Luogo": "Bolognina",
    "Emozione": "Disagio",
    "Fascia_eta": "26-35",
    "Sesso": "Donna",
    "Occupazione": "Studente/ssa",
    "Anni_Bologna": "Sono studente/ssa fuori sede",
    "Dove_cresciuto": "Altra città (o provincia) in Italia",
    "Quartiere_Bologna": "Bolognina",
    "Titolo_studio": "Laurea triennale",
    "Commento": "Fastidio, troppi turisti che vengono qui a mangiare e a inquinare il territorio"
  },
  {
    "ID": 62,
    "Luogo": "Piazza Lucio Dalla",
    "Emozione": "Accettazione",
    "Fascia_eta": "26-35",
    "Sesso": "Donna",
    "Occupazione": "Studente/ssa",
    "Anni_Bologna": "Sono studente/ssa fuori sede",
    "Dove_cresciuto": "Altra città (o provincia) in Italia",
    "Quartiere_Bologna": "Bolognina",
    "Titolo_studio": "Laurea triennale",
    "Commento": "Le persone che vogliono una città diversa, svincolarla alla gentrificazione e creare spazi alternativi e veramente nostri, ad uso pubblico e gratuito"
  },
  {
    "ID": 63,
    "Luogo": "La Zona Universitaria",
    "Emozione": "Cambiamento",
    "Fascia_eta": "26-35",
    "Sesso": "Donna",
    "Occupazione": "Studente/ssa",
    "Anni_Bologna": "Sono studente/ssa fuori sede",
    "Dove_cresciuto": "Altra città (o provincia) in Italia",
    "Quartiere_Bologna": "Bolognina",
    "Titolo_studio": "Laurea triennale",
    "Commento": "La sento più mia (via Zamboni) probabilmente per aver preso parte al festival dell'antropologia"
  },
  {
    "ID": 64,
    "Luogo": "Centro Civico e Villa Torchi",
    "Emozione": "Felicità",
    "Fascia_eta": "36-45",
    "Sesso": "Donna",
    "Occupazione": "Occupato/a dipendente",
    "Anni_Bologna": "Sono nato/a e cresciuto/a qui",
    "Dove_cresciuto": "Bologna (o provincia)",
    "Quartiere_Bologna": "Corticella",
    "Titolo_studio": "Diploma di scuola superiore",
    "Commento": "Vissuto la mia adolescenza tra muretti e panchine"
  },
  {
    "ID": 65,
    "Luogo": "Bolognina",
    "Emozione": "Tristezza",
    "Fascia_eta": "36-45",
    "Sesso": "Donna",
    "Occupazione": "Occupato/a dipendente",
    "Anni_Bologna": "Sono nato/a e cresciuto/a qui",
    "Dove_cresciuto": "Bologna (o provincia)",
    "Quartiere_Bologna": "Corticella",
    "Titolo_studio": "Diploma di scuola superiore",
    "Commento": "Perdita di mio padre"
  },
  {
    "ID": 66,
    "Luogo": "Bologna Centro",
    "Emozione": "Disagio",
    "Fascia_eta": "36-45",
    "Sesso": "Donna",
    "Occupazione": "Occupato/a dipendente",
    "Anni_Bologna": "Sono nato/a e cresciuto/a qui",
    "Dove_cresciuto": "Bologna (o provincia)",
    "Quartiere_Bologna": "Corticella",
    "Titolo_studio": "Diploma di scuola superiore",
    "Commento": "Adesso che sono adulta è pericoloso e totalmente cambiato"
  },
  {
    "ID": 67,
    "Luogo": "Centro Civico e Villa Torchi",
    "Emozione": "Accettazione",
    "Fascia_eta": "36-45",
    "Sesso": "Donna",
    "Occupazione": "Occupato/a dipendente",
    "Anni_Bologna": "Sono nato/a e cresciuto/a qui",
    "Dove_cresciuto": "Bologna (o provincia)",
    "Quartiere_Bologna": "Corticella",
    "Titolo_studio": "Diploma di scuola superiore",
    "Commento": "La mia infanzia e adolescenza vissuta con semplicità. Senza cellulari ma soprattutto divertirsi con quello che avevamo"
  },
  {
    "ID": 68,
    "Luogo": "Centro Civico Corticella",
    "Emozione": "Cambiamento",
    "Fascia_eta": "36-45",
    "Sesso": "Donna",
    "Occupazione": "Occupato/a dipendente",
    "Anni_Bologna": "Sono nato/a e cresciuto/a qui",
    "Dove_cresciuto": "Bologna (o provincia)",
    "Quartiere_Bologna": "Corticella",
    "Titolo_studio": "Diploma di scuola superiore",
    "Commento": "Cambiato il luogo! Ora sembra quasi di dover avere paura per le persone che ci sono"
  },
  {
    "ID": 69,
    "Luogo": "Palazzo Dello Sport",
    "Emozione": "Felicità",
    "Fascia_eta": "Più di 65",
    "Sesso": "Uomo",
    "Occupazione": "Pensionato/a",
    "Anni_Bologna": "Ci vivo da più di 5 anni e non sono studente/ssa fuori sede",
    "Dove_cresciuto": "Bologna (o provincia)",
    "Quartiere_Bologna": "Bolognina",
    "Titolo_studio": "Diploma di scuola superiore",
    "Commento": "Ho vissuto i miei anni dai 16 ai 23 ...e i giardinetti erano i nostri social in presenza"
  },
  {
    "ID": 70,
    "Luogo": "Stazione Centrale",
    "Emozione": "Tristezza",
    "Fascia_eta": "Più di 65",
    "Sesso": "Uomo",
    "Occupazione": "Pensionato/a",
    "Anni_Bologna": "Ci vivo da più di 5 anni e non sono studente/ssa fuori sede",
    "Dove_cresciuto": "Bologna (o provincia)",
    "Quartiere_Bologna": "Bolognina",
    "Titolo_studio": "Diploma di scuola superiore",
    "Commento": "Io ero sul posto dopo 15/20 minuti dallo scoppio della bomba del 2 agosto. Mi sembrava un film, il caos, le sirene, la gente incredula, ambulanze, polizia, carabinieri, civili, un incubo... impresso nella mia memoria..."
  },
  {
    "ID": 71,
    "Luogo": "Piazza Verdi",
    "Emozione": "Disagio",
    "Fascia_eta": "Più di 65",
    "Sesso": "Uomo",
    "Occupazione": "Pensionato/a",
    "Anni_Bologna": "Ci vivo da più di 5 anni e non sono studente/ssa fuori sede",
    "Dove_cresciuto": "Bologna (o provincia)",
    "Quartiere_Bologna": "Bolognina",
    "Titolo_studio": "Diploma di scuola superiore",
    "Commento": "Sensazione di non essere a Bologna"
  },
  {
    "ID": 72,
    "Luogo": "Bologna Centro",
    "Emozione": "Accettazione",
    "Fascia_eta": "Più di 65",
    "Sesso": "Uomo",
    "Occupazione": "Pensionato/a",
    "Anni_Bologna": "Ci vivo da più di 5 anni e non sono studente/ssa fuori sede",
    "Dove_cresciuto": "Bologna (o provincia)",
    "Quartiere_Bologna": "Bolognina",
    "Titolo_studio": "Diploma di scuola superiore",
    "Commento": "Sicurezza, ordine, pulizia."
  },
  {
    "ID": 73,
    "Luogo": "Bolognina",
    "Emozione": "Cambiamento",
    "Fascia_eta": "Più di 65",
    "Sesso": "Uomo",
    "Occupazione": "Pensionato/a",
    "Anni_Bologna": "Ci vivo da più di 5 anni e non sono studente/ssa fuori sede",
    "Dove_cresciuto": "Bologna (o provincia)",
    "Quartiere_Bologna": "Bolognina",
    "Titolo_studio": "Diploma di scuola superiore",
    "Commento": "Luogo in peggio, degrado, insicurezza"
  },
  {
    "ID": 74,
    "Luogo": "Piazza Maggiore",
    "Emozione": "Felicità",
    "Fascia_eta": "18-25",
    "Sesso": "Donna",
    "Occupazione": "Studente/ssa",
    "Anni_Bologna": "Ci vivo da più di 5 anni e non sono studente/ssa fuori sede",
    "Dove_cresciuto": "Altra città (o provincia) in Emilia Romagna",
    "Quartiere_Bologna": "Corticella",
    "Titolo_studio": "Laurea triennale",
    "Commento": "Ogni volta che ci vado, mi sento a casa e parte di qualcosa"
  },
  {
    "ID": 75,
    "Luogo": "Quartiere Roveri",
    "Emozione": "Disagio",
    "Fascia_eta": "18-25",
    "Sesso": "Donna",
    "Occupazione": "Studente/ssa",
    "Anni_Bologna": "Ci vivo da più di 5 anni e non sono studente/ssa fuori sede",
    "Dove_cresciuto": "Altra città (o provincia) in Emilia Romagna",
    "Quartiere_Bologna": "Corticella",
    "Titolo_studio": "Laurea triennale",
    "Commento": "Freddo"
  },
  {
    "ID": 76,
    "Luogo": "Bologna Centro",
    "Emozione": "Accettazione",
    "Fascia_eta": "18-25",
    "Sesso": "Donna",
    "Occupazione": "Studente/ssa",
    "Anni_Bologna": "Ci vivo da più di 5 anni e non sono studente/ssa fuori sede",
    "Dove_cresciuto": "Altra città (o provincia) in Emilia Romagna",
    "Quartiere_Bologna": "Corticella",
    "Titolo_studio": "Laurea triennale",
    "Commento": "Pieno di persone comuni non giudicanti"
  },
  {
    "ID": 77,
    "Luogo": "Villa Angeletti",
    "Emozione": "Felicità",
    "Fascia_eta": "26-35",
    "Sesso": "Donna",
    "Occupazione": "Occupato/a dipendente",
    "Anni_Bologna": "Ci vivo da più di 5 anni e non sono studente/ssa fuori sede",
    "Dove_cresciuto": "Altra città (o provincia) in Italia",
    "Quartiere_Bologna": "Bolognina",
    "Titolo_studio": "Laurea magistrale o superiore",
    "Commento": "Ci sono andata a correre per la prima volta quando mi accorsi che mi piaceva il mio coinquilino: dopo qualche giorno, ci dichiarammo e stiamo insieme da cinque anni e mezzo. Ci torniamo spesso in Villa Angeletti per fare picnic, passeggiate, biciclettate fino a Castel Maggiore sul Lungo Navile"
  },
  {
    "ID": 78,
    "Luogo": "Piazza Verdi",
    "Emozione": "Tristezza",
    "Fascia_eta": "26-35",
    "Sesso": "Donna",
    "Occupazione": "Occupato/a dipendente",
    "Anni_Bologna": "Ci vivo da più di 5 anni e non sono studente/ssa fuori sede",
    "Dove_cresciuto": "Altra città (o provincia) in Italia",
    "Quartiere_Bologna": "Bolognina",
    "Titolo_studio": "Laurea magistrale o superiore",
    "Commento": "Ricevetti un rifiuto da un mio amico che mi faceva love bombing da mesi, alle Serre. Dopo qualche ora e una bottiglia di rosso, a Piazza Verdi raggiunsi i miei amici, raccontai della situazione e ebbi una crisi di pianto, con annesso autolesionismo con un mazzo di chiavi."
  },
  {
    "ID": 79,
    "Luogo": "Via Della Ghisliera",
    "Emozione": "Disagio",
    "Fascia_eta": "26-35",
    "Sesso": "Donna",
    "Occupazione": "Occupato/a dipendente",
    "Anni_Bologna": "Ci vivo da più di 5 anni e non sono studente/ssa fuori sede",
    "Dove_cresciuto": "Altra città (o provincia) in Italia",
    "Quartiere_Bologna": "Bolognina",
    "Titolo_studio": "Laurea magistrale o superiore",
    "Commento": "Provo questa sensazione ogni volta che ci passo di sera, mi sembra di essere seguita... O che posso perdermi tra quelle vie senza mai essere ritrovata"
  },
  {
    "ID": 80,
    "Luogo": "Bolognina",
    "Emozione": "Accettazione",
    "Fascia_eta": "26-35",
    "Sesso": "Donna",
    "Occupazione": "Occupato/a dipendente",
    "Anni_Bologna": "Ci vivo da più di 5 anni e non sono studente/ssa fuori sede",
    "Dove_cresciuto": "Altra città (o provincia) in Italia",
    "Quartiere_Bologna": "Bolognina",
    "Titolo_studio": "Laurea magistrale o superiore",
    "Commento": "Ci sono multiculturalismo, colori, localini piccoli e non turistificati, piazze, assemblee... Sento di avere un senso, di essere ancora capace di determinare il mio destino"
  },
  {
    "ID": 81,
    "Luogo": "Bologna Centro",
    "Emozione": "Cambiamento",
    "Fascia_eta": "26-35",
    "Sesso": "Donna",
    "Occupazione": "Occupato/a dipendente",
    "Anni_Bologna": "Ci vivo da più di 5 anni e non sono studente/ssa fuori sede",
    "Dove_cresciuto": "Altra città (o provincia) in Italia",
    "Quartiere_Bologna": "Bolognina",
    "Titolo_studio": "Laurea magistrale o superiore",
    "Commento": "È cambiato il luogo: mangiatoia per turisti, negozi di catene impersonali, ristoranti di datori di lavoro mafiosi e sfruttatori. Manca l'eleganza dei primi anni, l'umanità e la provincialità buona che rendevano Piazza Maggiore la piazza di un paesone, non la sorella cattiva del Duomo di Milano"
  },
  {
    "ID": 82,
    "Luogo": "Ospedale Maggiore",
    "Emozione": "Tristezza",
    "Fascia_eta": "Più di 65",
    "Sesso": "Donna",
    "Occupazione": "Pensionato/a",
    "Anni_Bologna": "Ci vivo da più di 5 anni e non sono studente/ssa fuori sede",
    "Dove_cresciuto": "Bologna (o provincia)",
    "Quartiere_Bologna": "Corticella",
    "Titolo_studio": "Diploma di scuola superiore",
    "Commento": "Mio papà alla camera mortuaria alla medicina legale"
  },
  {
    "ID": 83,
    "Luogo": "Bologna Centro",
    "Emozione": "Disagio",
    "Fascia_eta": "Più di 65",
    "Sesso": "Donna",
    "Occupazione": "Pensionato/a",
    "Anni_Bologna": "Ci vivo da più di 5 anni e non sono studente/ssa fuori sede",
    "Dove_cresciuto": "Bologna (o provincia)",
    "Quartiere_Bologna": "Corticella",
    "Titolo_studio": "Diploma di scuola superiore",
    "Commento": "Una passeggiata per le vie del centro non più piacevole"
  },
  {
    "ID": 84,
    "Luogo": "Corticella",
    "Emozione": "Accettazione",
    "Fascia_eta": "Più di 65",
    "Sesso": "Donna",
    "Occupazione": "Pensionato/a",
    "Anni_Bologna": "Ci vivo da più di 5 anni e non sono studente/ssa fuori sede",
    "Dove_cresciuto": "Bologna (o provincia)",
    "Quartiere_Bologna": "Corticella",
    "Titolo_studio": "Diploma di scuola superiore",
    "Commento": "Il parco, i vicini di casa"
  },
  {
    "ID": 85,
    "Luogo": "Bologna Centro",
    "Emozione": "Cambiamento",
    "Fascia_eta": "Più di 65",
    "Sesso": "Donna",
    "Occupazione": "Pensionato/a",
    "Anni_Bologna": "Ci vivo da più di 5 anni e non sono studente/ssa fuori sede",
    "Dove_cresciuto": "Bologna (o provincia)",
    "Quartiere_Bologna": "Corticella",
    "Titolo_studio": "Diploma di scuola superiore",
    "Commento": "La maleducazione delle persone e l'incuria per le cose comuni"
  },
  {
    "ID": 86,
    "Luogo": "Via Mascarella",
    "Emozione": "Felicità",
    "Fascia_eta": "26-35",
    "Sesso": "Donna",
    "Occupazione": "Occupato autonomo (libero/a professionista, imprenditore/trice, artigiano/a)",
    "Anni_Bologna": "Ci vivo da più di 5 anni e non sono studente/ssa fuori sede",
    "Dove_cresciuto": "Altra città (o provincia) in Italia",
    "Quartiere_Bologna": "Bolognina",
    "Titolo_studio": "Laurea magistrale o superiore",
    "Commento": "Al Bar Modo e al Bar L'Ortica ci si incontrava spesso in aperitivo con gli amici che, come me, vivevano in zona."
  },
  {
    "ID": 87,
    "Luogo": "Via Milazzo",
    "Emozione": "Tristezza",
    "Fascia_eta": "26-35",
    "Sesso": "Donna",
    "Occupazione": "Occupato autonomo (libero/a professionista, imprenditore/trice, artigiano/a)",
    "Anni_Bologna": "Ci vivo da più di 5 anni e non sono studente/ssa fuori sede",
    "Dove_cresciuto": "Altra città (o provincia) in Italia",
    "Quartiere_Bologna": "Bolognina",
    "Titolo_studio": "Laurea magistrale o superiore",
    "Commento": "In quella via la mia prima casa a Bologna, piena di ricordi belli e brutti"
  },
  {
    "ID": 88,
    "Luogo": "Piazza Maggiore",
    "Emozione": "Disagio",
    "Fascia_eta": "26-35",
    "Sesso": "Donna",
    "Occupazione": "Occupato autonomo (libero/a professionista, imprenditore/trice, artigiano/a)",
    "Anni_Bologna": "Ci vivo da più di 5 anni e non sono studente/ssa fuori sede",
    "Dove_cresciuto": "Altra città (o provincia) in Italia",
    "Quartiere_Bologna": "Bolognina",
    "Titolo_studio": "Laurea magistrale o superiore",
    "Commento": "La primissima volta che l'ho vista! Era il giorno di San Petronio, arrivavo a Bologna dall'Abruzzo e, dopo un viaggio stancante, ero uscita in centro la sera per una prima visita della città. Erano appena finiti i fuochi d'artificio e tantissima gente si disperdeva dalla piazza verso le vie circostanti, c'era buio, non è stato un bel primo impatto"
  },
  {
    "ID": 89,
    "Luogo": "Via Parisio 28",
    "Emozione": "Accettazione",
    "Fascia_eta": "26-35",
    "Sesso": "Donna",
    "Occupazione": "Occupato autonomo (libero/a professionista, imprenditore/trice, artigiano/a)",
    "Anni_Bologna": "Ci vivo da più di 5 anni e non sono studente/ssa fuori sede",
    "Dove_cresciuto": "Altra città (o provincia) in Italia",
    "Quartiere_Bologna": "Bolognina",
    "Titolo_studio": "Laurea magistrale o superiore",
    "Commento": "C'è la Scuola di formazione in Psicoterapia che ho frequentato!"
  },
  {
    "ID": 90,
    "Luogo": "Piazza Verdi",
    "Emozione": "Cambiamento",
    "Fascia_eta": "26-35",
    "Sesso": "Donna",
    "Occupazione": "Occupato autonomo (libero/a professionista, imprenditore/trice, artigiano/a)",
    "Anni_Bologna": "Ci vivo da più di 5 anni e non sono studente/ssa fuori sede",
    "Dove_cresciuto": "Altra città (o provincia) in Italia",
    "Quartiere_Bologna": "Bolognina",
    "Titolo_studio": "Laurea magistrale o superiore",
    "Commento": "Non l'ho mai vissuta da studentessa, e da adulta mi fa sentire un po' a disagio, sento un po' di paura attraversando quella strada"
  },
  {
    "ID": 91,
    "Luogo": "Piazza San Francesco",
    "Emozione": "Felicità",
    "Fascia_eta": "18-25",
    "Sesso": "Donna",
    "Occupazione": "Studente/ssa",
    "Anni_Bologna": "Sono studente/ssa fuori sede",
    "Dove_cresciuto": "Altra città (o provincia) in Italia",
    "Quartiere_Bologna": "Bolognina",
    "Titolo_studio": "Diploma di scuola superiore",
    "Commento": "Mi ci sono innamorata!"
  },
  {
    "ID": 92,
    "Luogo": "Stazione Centrale",
    "Emozione": "Disagio",
    "Fascia_eta": "18-25",
    "Sesso": "Donna",
    "Occupazione": "Studente/ssa",
    "Anni_Bologna": "Sono studente/ssa fuori sede",
    "Dove_cresciuto": "Altra città (o provincia) in Italia",
    "Quartiere_Bologna": "Bolognina",
    "Titolo_studio": "Diploma di scuola superiore",
    "Commento": "Inquietante"
  },
  {
    "ID": 93,
    "Luogo": "La Zona Universitaria",
    "Emozione": "Accettazione",
    "Fascia_eta": "18-25",
    "Sesso": "Donna",
    "Occupazione": "Studente/ssa",
    "Anni_Bologna": "Sono studente/ssa fuori sede",
    "Dove_cresciuto": "Altra città (o provincia) in Italia",
    "Quartiere_Bologna": "Bolognina",
    "Titolo_studio": "Diploma di scuola superiore",
    "Commento": "Essendo così popolata da studenti e giovani mi sembra che nessuno mi giudicherà"
  },
  {
    "ID": 94,
    "Luogo": "Riva di Reno",
    "Emozione": "Cambiamento",
    "Fascia_eta": "18-25",
    "Sesso": "Donna",
    "Occupazione": "Studente/ssa",
    "Anni_Bologna": "Sono studente/ssa fuori sede",
    "Dove_cresciuto": "Altra città (o provincia) in Italia",
    "Quartiere_Bologna": "Bolognina",
    "Titolo_studio": "Diploma di scuola superiore",
    "Commento": "Prima mi inquietava ma ora no"
  },
  {
    "ID": 95,
    "Luogo": "Giardino San Leonardo",
    "Emozione": "Felicità",
    "Fascia_eta": "18-25",
    "Sesso": "Altro",
    "Occupazione": "Studente/ssa",
    "Anni_Bologna": "Sono studente/ssa fuori sede",
    "Dove_cresciuto": "Altra città (o provincia) in Emilia Romagna",
    "Quartiere_Bologna": "Bolognina",
    "Titolo_studio": "Laurea triennale",
    "Commento": "Ho avuto una delle uscite più belle della mia vita, conoscendo una persona e parlandoci per 7 ore filate, come se fossimo amici di una vita, parlando di tutto ed entrando l'uno nel cervello dell'altra. Più o meno a marzo di quest'anno."
  },
  {
    "ID": 96,
    "Luogo": "Parco della Montagnola",
    "Emozione": "Tristezza",
    "Fascia_eta": "18-25",
    "Sesso": "Altro",
    "Occupazione": "Studente/ssa",
    "Anni_Bologna": "Sono studente/ssa fuori sede",
    "Dove_cresciuto": "Altra città (o provincia) in Emilia Romagna",
    "Quartiere_Bologna": "Bolognina",
    "Titolo_studio": "Laurea triennale",
    "Commento": "È il luogo in cui mi si è rotto il cuore per la prima volta, sono stato lasciato seduto su una panchina, ed ora è un ricordo costante ogni volta che ci passo."
  },
  {
    "ID": 97,
    "Luogo": "Galleria Cavour",
    "Emozione": "Disagio",
    "Fascia_eta": "18-25",
    "Sesso": "Altro",
    "Occupazione": "Studente/ssa",
    "Anni_Bologna": "Sono studente/ssa fuori sede",
    "Dove_cresciuto": "Altra città (o provincia) in Emilia Romagna",
    "Quartiere_Bologna": "Bolognina",
    "Titolo_studio": "Laurea triennale",
    "Commento": "Disagio, gli sguardi delle persone che vedono una studentessa come se non appartenesse a quel posto, come se la povertà fosse un problema da odiare."
  },
  {
    "ID": 98,
    "Luogo": "Biblioteca Delle Donne",
    "Emozione": "Accettazione",
    "Fascia_eta": "18-25",
    "Sesso": "Altro",
    "Occupazione": "Studente/ssa",
    "Anni_Bologna": "Sono studente/ssa fuori sede",
    "Dove_cresciuto": "Altra città (o provincia) in Emilia Romagna",
    "Quartiere_Bologna": "Bolognina",
    "Titolo_studio": "Laurea triennale",
    "Commento": "Ci ho fatto il tirocinio in triennale, ed è davvero diventato un posto in cui mi son sentito a casa, un ambiente genuino e pieno di persone buone"
  },
  {
    "ID": 99,
    "Luogo": "Giardini Margherita",
    "Emozione": "Cambiamento",
    "Fascia_eta": "18-25",
    "Sesso": "Altro",
    "Occupazione": "Studente/ssa",
    "Anni_Bologna": "Sono studente/ssa fuori sede",
    "Dove_cresciuto": "Altra città (o provincia) in Emilia Romagna",
    "Quartiere_Bologna": "Bolognina",
    "Titolo_studio": "Laurea triennale",
    "Commento": "Sono cambiato io, li ho esplorati e conosciuti, e questo mi permette di essere cresciuto anche quando ci torno, più spesso di quanto potessi in passato"
  },
  {
    "ID": 100,
    "Luogo": "Circolo Iqbal Masih",
    "Emozione": "Felicità",
    "Fascia_eta": "56-65",
    "Sesso": "Donna",
    "Occupazione": "Occupato autonomo (libero/a professionista, imprenditore/trice, artigiano/a)",
    "Anni_Bologna": "Ci vivo da più di 5 anni e non sono studente/ssa fuori sede",
    "Dove_cresciuto": "Altra città (o provincia) in Italia",
    "Quartiere_Bologna": "Bolognina",
    "Titolo_studio": "Laurea magistrale o superiore",
    "Commento": "Nulla di particolare, una volta nei pub, si faceva anche politica, si creavano legami. Ora solo magnifici"
  },
  {
    "ID": 101,
    "Luogo": "Stazione Centrale",
    "Emozione": "Tristezza",
    "Fascia_eta": "56-65",
    "Sesso": "Donna",
    "Occupazione": "Occupato autonomo (libero/a professionista, imprenditore/trice, artigiano/a)",
    "Anni_Bologna": "Ci vivo da più di 5 anni e non sono studente/ssa fuori sede",
    "Dove_cresciuto": "Altra città (o provincia) in Italia",
    "Quartiere_Bologna": "Bolognina",
    "Titolo_studio": "Laurea magistrale o superiore",
    "Commento": "La strage"
  },
  {
    "ID": 102,
    "Luogo": "Osteria Del Sole",
    "Emozione": "Disagio",
    "Fascia_eta": "56-65",
    "Sesso": "Donna",
    "Occupazione": "Occupato autonomo (libero/a professionista, imprenditore/trice, artigiano/a)",
    "Anni_Bologna": "Ci vivo da più di 5 anni e non sono studente/ssa fuori sede",
    "Dove_cresciuto": "Altra città (o provincia) in Italia",
    "Quartiere_Bologna": "Bolognina",
    "Titolo_studio": "Laurea magistrale o superiore",
    "Commento": "Vi era distinzione tra la zona riservata ai \"notabili\" e quella per gli studenti. Si percepiva proprio il divario sociale"
  },
  {
    "ID": 103,
    "Luogo": "Bologna Centro",
    "Emozione": "Cambiamento",
    "Fascia_eta": "56-65",
    "Sesso": "Donna",
    "Occupazione": "Occupato autonomo (libero/a professionista, imprenditore/trice, artigiano/a)",
    "Anni_Bologna": "Ci vivo da più di 5 anni e non sono studente/ssa fuori sede",
    "Dove_cresciuto": "Altra città (o provincia) in Italia",
    "Quartiere_Bologna": "Bolognina",
    "Titolo_studio": "Laurea magistrale o superiore",
    "Commento": "È diventata una città per turisti e per ricchi"
  },
  {
    "ID": 104,
    "Luogo": "Corte D'appello di Bologna",
    "Emozione": "Felicità",
    "Fascia_eta": "56-65",
    "Sesso": "Donna",
    "Occupazione": "Occupato/a dipendente",
    "Anni_Bologna": "Ci vivo da più di 5 anni e non sono studente/ssa fuori sede",
    "Dove_cresciuto": "Altra città (o provincia) in Italia",
    "Quartiere_Bologna": "Bolognina",
    "Titolo_studio": "Diploma di scuola superiore",
    "Commento": "Matrimonio mio e di amici"
  },
  {
    "ID": 105,
    "Luogo": "Ospedale Sant'orsola",
    "Emozione": "Tristezza",
    "Fascia_eta": "56-65",
    "Sesso": "Donna",
    "Occupazione": "Occupato/a dipendente",
    "Anni_Bologna": "Ci vivo da più di 5 anni e non sono studente/ssa fuori sede",
    "Dove_cresciuto": "Altra città (o provincia) in Italia",
    "Quartiere_Bologna": "Bolognina",
    "Titolo_studio": "Diploma di scuola superiore",
    "Commento": "Per la perdita di persone care"
  },
  {
    "ID": 106,
    "Luogo": "Dopolavoro Ferroviario",
    "Emozione": "Accettazione",
    "Fascia_eta": "56-65",
    "Sesso": "Donna",
    "Occupazione": "Occupato/a dipendente",
    "Anni_Bologna": "Ci vivo da più di 5 anni e non sono studente/ssa fuori sede",
    "Dove_cresciuto": "Altra città (o provincia) in Italia",
    "Quartiere_Bologna": "Bolognina",
    "Titolo_studio": "Diploma di scuola superiore",
    "Commento": "Lo frequento fin dal mio arrivo, il centro"
  },
  {
    "ID": 107,
    "Luogo": "Bologna Centro",
    "Emozione": "Cambiamento",
    "Fascia_eta": "56-65",
    "Sesso": "Donna",
    "Occupazione": "Occupato/a dipendente",
    "Anni_Bologna": "Ci vivo da più di 5 anni e non sono studente/ssa fuori sede",
    "Dove_cresciuto": "Altra città (o provincia) in Italia",
    "Quartiere_Bologna": "Bolognina",
    "Titolo_studio": "Diploma di scuola superiore",
    "Commento": "Entrambe"
  },
  {
    "ID": 108,
    "Luogo": "Via Zamboni",
    "Emozione": "Felicità",
    "Fascia_eta": "56-65",
    "Sesso": "Donna",
    "Occupazione": "Occupato/a dipendente",
    "Anni_Bologna": "Ci vivo da più di 5 anni e non sono studente/ssa fuori sede",
    "Dove_cresciuto": "Altra città (o provincia) in Italia",
    "Quartiere_Bologna": "Corticella",
    "Titolo_studio": "Laurea magistrale o superiore",
    "Commento": "Ho frequentato il corso di laurea in Scienze Geologiche e mi sono laureata lì nel 1996"
  },
  {
    "ID": 109,
    "Luogo": "San Lazzaro, Via Emilia 51",
    "Emozione": "Tristezza",
    "Fascia_eta": "56-65",
    "Sesso": "Donna",
    "Occupazione": "Occupato/a dipendente",
    "Anni_Bologna": "Ci vivo da più di 5 anni e non sono studente/ssa fuori sede",
    "Dove_cresciuto": "Altra città (o provincia) in Italia",
    "Quartiere_Bologna": "Corticella",
    "Titolo_studio": "Laurea magistrale o superiore",
    "Commento": "Ho perso il bimbo che portavo in grembo nel 2012."
  },
  {
    "ID": 110,
    "Luogo": "Via Zamboni",
    "Emozione": "Disagio",
    "Fascia_eta": "56-65",
    "Sesso": "Donna",
    "Occupazione": "Occupato/a dipendente",
    "Anni_Bologna": "Ci vivo da più di 5 anni e non sono studente/ssa fuori sede",
    "Dove_cresciuto": "Altra città (o provincia) in Italia",
    "Quartiere_Bologna": "Corticella",
    "Titolo_studio": "Laurea magistrale o superiore",
    "Commento": "Disorientamento e nostalgia all'inizio dell'università"
  },
  {
    "ID": 111,
    "Luogo": "Via Zamboni",
    "Emozione": "Accettazione",
    "Fascia_eta": "56-65",
    "Sesso": "Donna",
    "Occupazione": "Occupato/a dipendente",
    "Anni_Bologna": "Ci vivo da più di 5 anni e non sono studente/ssa fuori sede",
    "Dove_cresciuto": "Altra città (o provincia) in Italia",
    "Quartiere_Bologna": "Corticella",
    "Titolo_studio": "Laurea magistrale o superiore",
    "Commento": "L'esperienza universitaria mi ha maturata"
  },
  {
    "ID": 112,
    "Luogo": "Via D'Azeglio",
    "Emozione": "Felicità",
    "Fascia_eta": "Più di 65",
    "Sesso": "Donna",
    "Occupazione": "Pensionato/a",
    "Anni_Bologna": "Ci vivo da più di 5 anni e non sono studente/ssa fuori sede",
    "Dove_cresciuto": "Bologna (o provincia)",
    "Quartiere_Bologna": "Lame",
    "Titolo_studio": "Diploma di scuola superiore",
    "Commento": "Esattamente la nascita dei miei due figli"
  },
  {
    "ID": 113,
    "Luogo": "Bologna Centro",
    "Emozione": "Cambiamento",
    "Fascia_eta": "Più di 65",
    "Sesso": "Donna",
    "Occupazione": "Pensionato/a",
    "Anni_Bologna": "Ci vivo da più di 5 anni e non sono studente/ssa fuori sede",
    "Dove_cresciuto": "Bologna (o provincia)",
    "Quartiere_Bologna": "Lame",
    "Titolo_studio": "Diploma di scuola superiore",
    "Commento": "Siamo cambiati entrambi"
  },
  {
    "ID": 114,
    "Luogo": "Dopolavoro Ferroviario",
    "Emozione": "Felicità",
    "Fascia_eta": "26-35",
    "Sesso": "Donna",
    "Occupazione": "Occupato/a dipendente",
    "Anni_Bologna": "Ci vivo da più di 5 anni e non sono studente/ssa fuori sede",
    "Dove_cresciuto": "Altra città (o provincia) in Italia",
    "Quartiere_Bologna": "Bolognina",
    "Titolo_studio": "Laurea magistrale o superiore",
    "Commento": "Lì abbiamo conosciuto quelli che ora sono i nostri amici"
  },
  {
    "ID": 115,
    "Luogo": "Via Mazzini",
    "Emozione": "Tristezza",
    "Fascia_eta": "26-35",
    "Sesso": "Donna",
    "Occupazione": "Occupato/a dipendente",
    "Anni_Bologna": "Ci vivo da più di 5 anni e non sono studente/ssa fuori sede",
    "Dove_cresciuto": "Altra città (o provincia) in Italia",
    "Quartiere_Bologna": "Bolognina",
    "Titolo_studio": "Laurea magistrale o superiore",
    "Commento": "C'era molta solitudine"
  },
  {
    "ID": 116,
    "Luogo": "Parco della Montagnola",
    "Emozione": "Disagio",
    "Fascia_eta": "26-35",
    "Sesso": "Donna",
    "Occupazione": "Occupato/a dipendente",
    "Anni_Bologna": "Ci vivo da più di 5 anni e non sono studente/ssa fuori sede",
    "Dove_cresciuto": "Altra città (o provincia) in Italia",
    "Quartiere_Bologna": "Bolognina",
    "Titolo_studio": "Laurea magistrale o superiore",
    "Commento": "In occasione di eventi vedevo molta freddezza in generale verso chi era lì senza esser \"parte del gruppo\""
  },
  {
    "ID": 117,
    "Luogo": "Bolognina",
    "Emozione": "Accettazione",
    "Fascia_eta": "26-35",
    "Sesso": "Donna",
    "Occupazione": "Occupato/a dipendente",
    "Anni_Bologna": "Ci vivo da più di 5 anni e non sono studente/ssa fuori sede",
    "Dove_cresciuto": "Altra città (o provincia) in Italia",
    "Quartiere_Bologna": "Bolognina",
    "Titolo_studio": "Laurea magistrale o superiore",
    "Commento": "Qui si mantiene ancora uno spirito di comunità e gentilezza verso il prossimo"
  },
  {
    "ID": 118,
    "Luogo": "Bologna Centro",
    "Emozione": "Cambiamento",
    "Fascia_eta": "26-35",
    "Sesso": "Donna",
    "Occupazione": "Occupato/a dipendente",
    "Anni_Bologna": "Ci vivo da più di 5 anni e non sono studente/ssa fuori sede",
    "Dove_cresciuto": "Altra città (o provincia) in Italia",
    "Quartiere_Bologna": "Bolognina",
    "Titolo_studio": "Laurea magistrale o superiore",
    "Commento": "Prima mi piaceva frequentarlo di più specialmente nel week end, adesso preferisco vivere il quartiere"
  },
  {
    "ID": 119,
    "Luogo": "Corte D'appello di Bologna",
    "Emozione": "Felicità",
    "Fascia_eta": "36-45",
    "Sesso": "Donna",
    "Occupazione": "Occupato/a dipendente",
    "Anni_Bologna": "Ci vivo da più di 5 anni e non sono studente/ssa fuori sede",
    "Dove_cresciuto": "Altra città (o provincia) in Italia",
    "Quartiere_Bologna": "Corticella",
    "Titolo_studio": "Laurea magistrale o superiore",
    "Commento": "Abilitazione all'esercizio della professione forense"
  },
  {
    "ID": 120,
    "Luogo": "Ospedale Maggiore",
    "Emozione": "Tristezza",
    "Fascia_eta": "36-45",
    "Sesso": "Donna",
    "Occupazione": "Occupato/a dipendente",
    "Anni_Bologna": "Ci vivo da più di 5 anni e non sono studente/ssa fuori sede",
    "Dove_cresciuto": "Altra città (o provincia) in Italia",
    "Quartiere_Bologna": "Corticella",
    "Titolo_studio": "Laurea magistrale o superiore",
    "Commento": ""
  },
  {
    "ID": 121,
    "Luogo": "Centro Civico e Villa Torchi",
    "Emozione": "Accettazione",
    "Fascia_eta": "36-45",
    "Sesso": "Donna",
    "Occupazione": "Occupato/a dipendente",
    "Anni_Bologna": "Ci vivo da più di 5 anni e non sono studente/ssa fuori sede",
    "Dove_cresciuto": "Altra città (o provincia) in Italia",
    "Quartiere_Bologna": "Corticella",
    "Titolo_studio": "Laurea magistrale o superiore",
    "Commento": "È un posto dove vado spesso perché i miei bimbi frequentano le scuole vicine. Negli anni ho consolidato rapporti significativi con alcune famiglie del quartiere. Corticella ha un'identità forte e offre momenti importanti di condivisione."
  },
  {
    "ID": 122,
    "Luogo": "Bologna Centro",
    "Emozione": "Cambiamento",
    "Fascia_eta": "36-45",
    "Sesso": "Donna",
    "Occupazione": "Occupato/a dipendente",
    "Anni_Bologna": "Ci vivo da più di 5 anni e non sono studente/ssa fuori sede",
    "Dove_cresciuto": "Altra città (o provincia) in Italia",
    "Quartiere_Bologna": "Corticella",
    "Titolo_studio": "Laurea magistrale o superiore",
    "Commento": "Entrambe le cose. Percepisco maggiore degrado e insicurezza, soprattutto nella zona di Piazza XX settembre. Ma penso siano anche cambiate le mie abitudini e le mie esigenze, dopo aver messo su famiglia."
  },
  {
    "ID": 123,
    "Luogo": "Ippodromo",
    "Emozione": "Felicità",
    "Fascia_eta": "56-65",
    "Sesso": "Donna",
    "Occupazione": "Pensionato/a",
    "Anni_Bologna": "Sono nato/a e cresciuto/a qui",
    "Dove_cresciuto": "Bologna (o provincia)",
    "Quartiere_Bologna": "Bolognina",
    "Titolo_studio": "Laurea magistrale o superiore",
    "Commento": "Da piccola giocavo nel parco e andavo a vedere i cavalli"
  },
  {
    "ID": 124,
    "Luogo": "Stazione Centrale",
    "Emozione": "Tristezza",
    "Fascia_eta": "56-65",
    "Sesso": "Donna",
    "Occupazione": "Pensionato/a",
    "Anni_Bologna": "Sono nato/a e cresciuto/a qui",
    "Dove_cresciuto": "Bologna (o provincia)",
    "Quartiere_Bologna": "Bolognina",
    "Titolo_studio": "Laurea magistrale o superiore",
    "Commento": "Mio padre era ferroviere quando esplose la bomba"
  },
  {
    "ID": 125,
    "Luogo": "Parco della Montagnola",
    "Emozione": "Disagio",
    "Fascia_eta": "56-65",
    "Sesso": "Donna",
    "Occupazione": "Pensionato/a",
    "Anni_Bologna": "Sono nato/a e cresciuto/a qui",
    "Dove_cresciuto": "Bologna (o provincia)",
    "Quartiere_Bologna": "Bolognina",
    "Titolo_studio": "Laurea magistrale o superiore",
    "Commento": "Senso di insicurezza andando a prendere mio nipote alla scuola materna"
  },
  {
    "ID": 126,
    "Luogo": "Bologna Centro",
    "Emozione": "Accettazione",
    "Fascia_eta": "56-65",
    "Sesso": "Donna",
    "Occupazione": "Pensionato/a",
    "Anni_Bologna": "Sono nato/a e cresciuto/a qui",
    "Dove_cresciuto": "Bologna (o provincia)",
    "Quartiere_Bologna": "Bolognina",
    "Titolo_studio": "Laurea magistrale o superiore",
    "Commento": "Mi sento a casa"
  },
  {
    "ID": 127,
    "Luogo": "Stazione Centrale",
    "Emozione": "Cambiamento",
    "Fascia_eta": "56-65",
    "Sesso": "Donna",
    "Occupazione": "Pensionato/a",
    "Anni_Bologna": "Sono nato/a e cresciuto/a qui",
    "Dove_cresciuto": "Bologna (o provincia)",
    "Quartiere_Bologna": "Bolognina",
    "Titolo_studio": "Laurea magistrale o superiore",
    "Commento": "Entrambe le cose"
  },
  {
    "ID": 128,
    "Luogo": "Via Serlio",
    "Emozione": "Felicità",
    "Fascia_eta": "46-55",
    "Sesso": "Donna",
    "Occupazione": "Occupato/a dipendente",
    "Anni_Bologna": "Ci vivo da più di 5 anni e non sono studente/ssa fuori sede",
    "Dove_cresciuto": "Altra città (o provincia) in Italia",
    "Quartiere_Bologna": "Bolognina",
    "Titolo_studio": "Laurea triennale",
    "Commento": "Ho acquistato la mia casetta"
  },
  {
    "ID": 129,
    "Luogo": "Carcere Dozza",
    "Emozione": "Tristezza",
    "Fascia_eta": "46-55",
    "Sesso": "Donna",
    "Occupazione": "Occupato/a dipendente",
    "Anni_Bologna": "Ci vivo da più di 5 anni e non sono studente/ssa fuori sede",
    "Dove_cresciuto": "Altra città (o provincia) in Italia",
    "Quartiere_Bologna": "Bolognina",
    "Titolo_studio": "Laurea triennale",
    "Commento": "Ho lavorato lì due anni, e la loro condizione era davvero inaccettabile. Ricordo anche un alunno che si è tolto la vita"
  },
  {
    "ID": 130,
    "Luogo": "Scuole Longhena",
    "Emozione": "Disagio",
    "Fascia_eta": "46-55",
    "Sesso": "Donna",
    "Occupazione": "Occupato/a dipendente",
    "Anni_Bologna": "Ci vivo da più di 5 anni e non sono studente/ssa fuori sede",
    "Dove_cresciuto": "Altra città (o provincia) in Italia",
    "Quartiere_Bologna": "Bolognina",
    "Titolo_studio": "Laurea triennale",
    "Commento": "Ho lavorato lì un anno e poi sono letteralmente scappata via. Così diverse dalle scuole della Bolognina, per composizione sociale ed etnica"
  },
  {
    "ID": 131,
    "Luogo": "Piazza Lucio Dalla",
    "Emozione": "Accettazione",
    "Fascia_eta": "46-55",
    "Sesso": "Donna",
    "Occupazione": "Occupato/a dipendente",
    "Anni_Bologna": "Ci vivo da più di 5 anni e non sono studente/ssa fuori sede",
    "Dove_cresciuto": "Altra città (o provincia) in Italia",
    "Quartiere_Bologna": "Bolognina",
    "Titolo_studio": "Laurea triennale",
    "Commento": "Bellissima e con la possibilità di conoscere il mondo intero"
  },
  {
    "ID": 132,
    "Luogo": "Via Antonio di Vincenzo",
    "Emozione": "Felicità",
    "Fascia_eta": "56-65",
    "Sesso": "Donna",
    "Occupazione": "Occupato/a dipendente",
    "Anni_Bologna": "Ci vivo da più di 5 anni e non sono studente/ssa fuori sede",
    "Dove_cresciuto": "Altra città (o provincia) in Italia",
    "Quartiere_Bologna": "Bolognina",
    "Titolo_studio": "Diploma di scuola superiore",
    "Commento": "È la scuola frequentata dai miei figli da piccoli tra gli anni 2000 e 2005, è stata una bella esperienza di relazioni e nel cortile della scuola sono nate anche amicizie durature con altri genitori."
  },
  {
    "ID": 133,
    "Luogo": "Via Marzabotto",
    "Emozione": "Tristezza",
    "Fascia_eta": "56-65",
    "Sesso": "Donna",
    "Occupazione": "Occupato/a dipendente",
    "Anni_Bologna": "Ci vivo da più di 5 anni e non sono studente/ssa fuori sede",
    "Dove_cresciuto": "Altra città (o provincia) in Italia",
    "Quartiere_Bologna": "Bolognina",
    "Titolo_studio": "Diploma di scuola superiore",
    "Commento": "Dove era nata la Casa del Popolo 20 pietre negli anni 2000. La fine di quella esperienza collettiva di riutilizzo temporaneo di spazi abbandonati. Ha costituito un luogo di incontro, mutuo soccorso e costruzioni di reti molto importanti per tutta la città e ha anche animato le lotte del \"comitato rigenerazione no speculazione\" per il bosco urbano dei prati di caprara"
  },
  {
    "ID": 134,
    "Luogo": "Carcere Dozza",
    "Emozione": "Disagio",
    "Fascia_eta": "56-65",
    "Sesso": "Donna",
    "Occupazione": "Occupato/a dipendente",
    "Anni_Bologna": "Ci vivo da più di 5 anni e non sono studente/ssa fuori sede",
    "Dove_cresciuto": "Altra città (o provincia) in Italia",
    "Quartiere_Bologna": "Bolognina",
    "Titolo_studio": "Diploma di scuola superiore",
    "Commento": "È il luogo del nostro quartiere dove ho avvertito un senso di isolamento, di mancanza di luoghi di incontro e di servizi di prossimità. Come staccato dalla città e dalla vitalità del nostro quartiere"
  },
  {
    "ID": 135,
    "Luogo": "Piazza Lucio Dalla",
    "Emozione": "Accettazione",
    "Fascia_eta": "56-65",
    "Sesso": "Donna",
    "Occupazione": "Occupato/a dipendente",
    "Anni_Bologna": "Ci vivo da più di 5 anni e non sono studente/ssa fuori sede",
    "Dove_cresciuto": "Altra città (o provincia) in Italia",
    "Quartiere_Bologna": "Bolognina",
    "Titolo_studio": "Diploma di scuola superiore",
    "Commento": "È una vera piazza pubblica, un luogo abitato e di incontro di tutta la gente del quartiere, dove ci sono ragazzi, bambini ma anche famiglie e anziani. Lo sento mio perché ho bisogno di spazi abitati e attraversati dalle persone."
  },
  {
    "ID": 136,
    "Luogo": "Bologna Centro",
    "Emozione": "Cambiamento",
    "Fascia_eta": "56-65",
    "Sesso": "Donna",
    "Occupazione": "Occupato/a dipendente",
    "Anni_Bologna": "Ci vivo da più di 5 anni e non sono studente/ssa fuori sede",
    "Dove_cresciuto": "Altra città (o provincia) in Italia",
    "Quartiere_Bologna": "Bolognina",
    "Titolo_studio": "Diploma di scuola superiore",
    "Commento": "Da studentessa universitaria era il mio riferimento come posto di incontro. In questo momento prevale nettamente come luogo di consumo. Bologna era il posto delle osterie adesso prevale il cibo di strada. Rimane un luogo bellissimo con iniziative straordinarie come il Cinema in Piazza ma sicuramente è molto diverso dal passato. Ma in positivo è cambiato anche il mio quartiere che offre molte più occasioni ludiche ed eventi culturali che in passato."
  },
  {
    "ID": 137,
    "Luogo": "Asilo S. M. Di Leuca di Via Cignani",
    "Emozione": "Felicità",
    "Fascia_eta": "56-65",
    "Sesso": "Uomo",
    "Occupazione": "Occupato/a dipendente",
    "Anni_Bologna": "Sono nato/a e cresciuto/a qui",
    "Dove_cresciuto": "Bologna (o provincia)",
    "Quartiere_Bologna": "Bolognina",
    "Titolo_studio": "Laurea triennale",
    "Commento": "Ci sono stati i miei figli."
  },
  {
    "ID": 138,
    "Luogo": "Via Del Battiferro",
    "Emozione": "Tristezza",
    "Fascia_eta": "56-65",
    "Sesso": "Uomo",
    "Occupazione": "Occupato/a dipendente",
    "Anni_Bologna": "Sono nato/a e cresciuto/a qui",
    "Dove_cresciuto": "Bologna (o provincia)",
    "Quartiere_Bologna": "Bolognina",
    "Titolo_studio": "Laurea triennale",
    "Commento": "C'era la casa dove ho vissuto prima di separarmi."
  },
  {
    "ID": 139,
    "Luogo": "Via Matteotti",
    "Emozione": "Disagio",
    "Fascia_eta": "56-65",
    "Sesso": "Uomo",
    "Occupazione": "Occupato/a dipendente",
    "Anni_Bologna": "Sono nato/a e cresciuto/a qui",
    "Dove_cresciuto": "Bologna (o provincia)",
    "Quartiere_Bologna": "Bolognina",
    "Titolo_studio": "Laurea triennale",
    "Commento": "Troppi extracomunitari e delinquenti."
  },
  {
    "ID": 140,
    "Luogo": "Via Augusto Murri",
    "Emozione": "Accettazione",
    "Fascia_eta": "56-65",
    "Sesso": "Uomo",
    "Occupazione": "Occupato/a dipendente",
    "Anni_Bologna": "Sono nato/a e cresciuto/a qui",
    "Dove_cresciuto": "Bologna (o provincia)",
    "Quartiere_Bologna": "Bolognina",
    "Titolo_studio": "Laurea triennale",
    "Commento": "Ci ho passato la maggior parte della mia vita."
  },
  {
    "ID": 141,
    "Luogo": "Bologna Centro",
    "Emozione": "Cambiamento",
    "Fascia_eta": "56-65",
    "Sesso": "Uomo",
    "Occupazione": "Occupato/a dipendente",
    "Anni_Bologna": "Sono nato/a e cresciuto/a qui",
    "Dove_cresciuto": "Bologna (o provincia)",
    "Quartiere_Bologna": "Bolognina",
    "Titolo_studio": "Laurea triennale",
    "Commento": "Tutto."
  },
  {
    "ID": 142,
    "Luogo": "Accademia di Belle Arti",
    "Emozione": "Felicità",
    "Fascia_eta": "Più di 65",
    "Sesso": "Donna",
    "Occupazione": "Pensionato/a",
    "Anni_Bologna": "Sono nato/a e cresciuto/a qui",
    "Dove_cresciuto": "Bologna (o provincia)",
    "Quartiere_Bologna": "Lame",
    "Titolo_studio": "Laurea magistrale o superiore",
    "Commento": "Studio, arte, amicizie importanti"
  },
  {
    "ID": 143,
    "Luogo": "Via D'Azeglio",
    "Emozione": "Tristezza",
    "Fascia_eta": "Più di 65",
    "Sesso": "Donna",
    "Occupazione": "Pensionato/a",
    "Anni_Bologna": "Sono nato/a e cresciuto/a qui",
    "Dove_cresciuto": "Bologna (o provincia)",
    "Quartiere_Bologna": "Lame",
    "Titolo_studio": "Laurea magistrale o superiore",
    "Commento": "Non incontrare più Lucio"
  },
  {
    "ID": 144,
    "Luogo": "Bologna Centro",
    "Emozione": "Disagio",
    "Fascia_eta": "Più di 65",
    "Sesso": "Donna",
    "Occupazione": "Pensionato/a",
    "Anni_Bologna": "Sono nato/a e cresciuto/a qui",
    "Dove_cresciuto": "Bologna (o provincia)",
    "Quartiere_Bologna": "Lame",
    "Titolo_studio": "Laurea magistrale o superiore",
    "Commento": "Gente disinteressata alle bellezze di Bologna e al rispetto per tutto ciò che è comune. I centri commerciali e le vie della cosiddetta movida: gente che mangia a tutte le ore chiassosa"
  },
  {
    "ID": 145,
    "Luogo": "Bologna Centro",
    "Emozione": "Accettazione",
    "Fascia_eta": "Più di 65",
    "Sesso": "Donna",
    "Occupazione": "Pensionato/a",
    "Anni_Bologna": "Sono nato/a e cresciuto/a qui",
    "Dove_cresciuto": "Bologna (o provincia)",
    "Quartiere_Bologna": "Lame",
    "Titolo_studio": "Laurea magistrale o superiore",
    "Commento": "Conoscere ogni angolo e incontrare persone amiche"
  },
  {
    "ID": 146,
    "Luogo": "Mercato Delle Erbe",
    "Emozione": "Cambiamento",
    "Fascia_eta": "Più di 65",
    "Sesso": "Donna",
    "Occupazione": "Pensionato/a",
    "Anni_Bologna": "Sono nato/a e cresciuto/a qui",
    "Dove_cresciuto": "Bologna (o provincia)",
    "Quartiere_Bologna": "Lame",
    "Titolo_studio": "Laurea magistrale o superiore",
    "Commento": "È cambiato il luogo"
  },
  {
    "ID": 147,
    "Luogo": "Porta S.felice",
    "Emozione": "Felicità",
    "Fascia_eta": "Più di 65",
    "Sesso": "Donna",
    "Occupazione": "Pensionato/a",
    "Anni_Bologna": "Sono nato/a e cresciuto/a qui",
    "Dove_cresciuto": "Bologna (o provincia)",
    "Quartiere_Bologna": "Lame",
    "Titolo_studio": "Diploma di scuola superiore",
    "Commento": "Ho abitato lì dai 10 ai 20 anni e il panorama della porta dalla mia finestra era fantastico"
  },
  {
    "ID": 148,
    "Luogo": "La Certosa",
    "Emozione": "Tristezza",
    "Fascia_eta": "Più di 65",
    "Sesso": "Donna",
    "Occupazione": "Pensionato/a",
    "Anni_Bologna": "Sono nato/a e cresciuto/a qui",
    "Dove_cresciuto": "Bologna (o provincia)",
    "Quartiere_Bologna": "Lame",
    "Titolo_studio": "Diploma di scuola superiore",
    "Commento": "Vi ho accompagnato i miei genitori e tanti amici purtroppo"
  },
  {
    "ID": 149,
    "Luogo": "Corticella",
    "Emozione": "Disagio",
    "Fascia_eta": "Più di 65",
    "Sesso": "Donna",
    "Occupazione": "Pensionato/a",
    "Anni_Bologna": "Sono nato/a e cresciuto/a qui",
    "Dove_cresciuto": "Bologna (o provincia)",
    "Quartiere_Bologna": "Lame",
    "Titolo_studio": "Diploma di scuola superiore",
    "Commento": "Il disordine urbanistico, la miscellanea di edifici con funzioni diverse e la mancanza di un tessuto di servizi e luoghi di aggregazione rendono la maggior parte delle periferie dei dormitori in cui muoversi e vivere la città a piedi è faticoso o addirittura pericoloso"
  },
  {
    "ID": 150,
    "Luogo": "Piazza Maggiore",
    "Emozione": "Accettazione",
    "Fascia_eta": "Più di 65",
    "Sesso": "Donna",
    "Occupazione": "Pensionato/a",
    "Anni_Bologna": "Sono nato/a e cresciuto/a qui",
    "Dove_cresciuto": "Bologna (o provincia)",
    "Quartiere_Bologna": "Lame",
    "Titolo_studio": "Diploma di scuola superiore",
    "Commento": "La sensazione di appartenenza ad una lunga storia"
  },
  {
    "ID": 151,
    "Luogo": "Ex Mercato Ortofrutticolo",
    "Emozione": "Cambiamento",
    "Fascia_eta": "Più di 65",
    "Sesso": "Donna",
    "Occupazione": "Pensionato/a",
    "Anni_Bologna": "Sono nato/a e cresciuto/a qui",
    "Dove_cresciuto": "Bologna (o provincia)",
    "Quartiere_Bologna": "Lame",
    "Titolo_studio": "Diploma di scuola superiore",
    "Commento": "Il luogo è cambiato e si è progressivamente riempito di enormi costruzioni molto diverse dal tessuto urbanistico della zona"
  },
  {
    "ID": 152,
    "Luogo": "Dopolavoro Ferroviario",
    "Emozione": "Felicità",
    "Fascia_eta": "36-45",
    "Sesso": "Uomo",
    "Occupazione": "Occupato autonomo (libero/a professionista, imprenditore/trice, artigiano/a)",
    "Anni_Bologna": "Sono nato/a e cresciuto/a qui",
    "Dove_cresciuto": "Bologna (o provincia)",
    "Quartiere_Bologna": "Bolognina",
    "Titolo_studio": "Laurea magistrale o superiore",
    "Commento": "Al parco con il nonno"
  },
  {
    "ID": 153,
    "Luogo": "Bologna Centro",
    "Emozione": "Disagio",
    "Fascia_eta": "36-45",
    "Sesso": "Uomo",
    "Occupazione": "Occupato autonomo (libero/a professionista, imprenditore/trice, artigiano/a)",
    "Anni_Bologna": "Sono nato/a e cresciuto/a qui",
    "Dove_cresciuto": "Bologna (o provincia)",
    "Quartiere_Bologna": "Bolognina",
    "Titolo_studio": "Laurea magistrale o superiore",
    "Commento": "La città è diventata cara e poco a misura delle persone che non sono ricche"
  },
  {
    "ID": 154,
    "Luogo": "Bolognina",
    "Emozione": "Accettazione",
    "Fascia_eta": "36-45",
    "Sesso": "Uomo",
    "Occupazione": "Occupato autonomo (libero/a professionista, imprenditore/trice, artigiano/a)",
    "Anni_Bologna": "Sono nato/a e cresciuto/a qui",
    "Dove_cresciuto": "Bologna (o provincia)",
    "Quartiere_Bologna": "Bolognina",
    "Titolo_studio": "Laurea magistrale o superiore",
    "Commento": "Un piccolo paese"
  },
  {
    "ID": 155,
    "Luogo": "Bologna Centro",
    "Emozione": "Cambiamento",
    "Fascia_eta": "36-45",
    "Sesso": "Uomo",
    "Occupazione": "Occupato autonomo (libero/a professionista, imprenditore/trice, artigiano/a)",
    "Anni_Bologna": "Sono nato/a e cresciuto/a qui",
    "Dove_cresciuto": "Bologna (o provincia)",
    "Quartiere_Bologna": "Bolognina",
    "Titolo_studio": "Laurea magistrale o superiore",
    "Commento": "Vedi sopra: città cara e elitaria"
  },
  {
    "ID": 156,
    "Luogo": "Oratorio di San Savino",
    "Emozione": "Felicità",
    "Fascia_eta": "56-65",
    "Sesso": "Uomo",
    "Occupazione": "Pensionato/a",
    "Anni_Bologna": "Ci vivo da più di 5 anni e non sono studente/ssa fuori sede",
    "Dove_cresciuto": "Bologna (o provincia)",
    "Quartiere_Bologna": "Corticella",
    "Titolo_studio": "Diploma di scuola superiore",
    "Commento": "È il luogo di Corticella dove ho passato in assoluto più tempo e che frequento tuttora"
  },
  {
    "ID": 157,
    "Luogo": "Stazione Centrale",
    "Emozione": "Tristezza",
    "Fascia_eta": "56-65",
    "Sesso": "Uomo",
    "Occupazione": "Pensionato/a",
    "Anni_Bologna": "Ci vivo da più di 5 anni e non sono studente/ssa fuori sede",
    "Dove_cresciuto": "Bologna (o provincia)",
    "Quartiere_Bologna": "Corticella",
    "Titolo_studio": "Diploma di scuola superiore",
    "Commento": "La strage del 2 agosto"
  },
  {
    "ID": 158,
    "Luogo": "Porta Galliera",
    "Emozione": "Disagio",
    "Fascia_eta": "56-65",
    "Sesso": "Uomo",
    "Occupazione": "Pensionato/a",
    "Anni_Bologna": "Ci vivo da più di 5 anni e non sono studente/ssa fuori sede",
    "Dove_cresciuto": "Bologna (o provincia)",
    "Quartiere_Bologna": "Corticella",
    "Titolo_studio": "Diploma di scuola superiore",
    "Commento": "Un po' di timore a passarci, soprattutto se c'è poca gente. La sensazione è che sia una zona dove la legalità è poco presente"
  },
  {
    "ID": 159,
    "Luogo": "Oratorio di San Savino",
    "Emozione": "Accettazione",
    "Fascia_eta": "56-65",
    "Sesso": "Uomo",
    "Occupazione": "Pensionato/a",
    "Anni_Bologna": "Ci vivo da più di 5 anni e non sono studente/ssa fuori sede",
    "Dove_cresciuto": "Bologna (o provincia)",
    "Quartiere_Bologna": "Corticella",
    "Titolo_studio": "Diploma di scuola superiore",
    "Commento": "Non sono stato solo fruitore, ma col tempo ne sono diventato anche protagonista"
  },
  {
    "ID": 160,
    "Luogo": "Bologna Centro",
    "Emozione": "Cambiamento",
    "Fascia_eta": "56-65",
    "Sesso": "Uomo",
    "Occupazione": "Pensionato/a",
    "Anni_Bologna": "Ci vivo da più di 5 anni e non sono studente/ssa fuori sede",
    "Dove_cresciuto": "Bologna (o provincia)",
    "Quartiere_Bologna": "Corticella",
    "Titolo_studio": "Diploma di scuola superiore",
    "Commento": "È cambiato il luogo: la maggiore presenza di turisti l'ha reso meno fruibile per i Bolognesi (costi della ristorazione aumentati e qualità più a dimensione turista)."
  },
  {
    "ID": 161,
    "Luogo": "Via San Vitale",
    "Emozione": "Felicità",
    "Fascia_eta": "Più di 65",
    "Sesso": "Donna",
    "Occupazione": "Pensionato/a",
    "Anni_Bologna": "Sono nato/a e cresciuto/a qui",
    "Dove_cresciuto": "Bologna (o provincia)",
    "Quartiere_Bologna": "Bolognina",
    "Titolo_studio": "Laurea magistrale o superiore",
    "Commento": "Abitavo lì ed ero felice di essere tornata a casa con mio figlio neonato - 1982"
  },
  {
    "ID": 162,
    "Luogo": " Chiesa del Sacro Cuore",
    "Emozione": "Tristezza",
    "Fascia_eta": "Più di 65",
    "Sesso": "Donna",
    "Occupazione": "Pensionato/a",
    "Anni_Bologna": "Sono nato/a e cresciuto/a qui",
    "Dove_cresciuto": "Bologna (o provincia)",
    "Quartiere_Bologna": "Bolognina",
    "Titolo_studio": "Laurea magistrale o superiore",
    "Commento": "Il funerale di mia madre quasi ottantenne. Tanta gente che le voleva bene. La convivenza di due sentimenti contrastanti: il sollievo e il dolore"
  },
  {
    "ID": 163,
    "Luogo": "ITC Rosa Luxemburg",
    "Emozione": "Disagio",
    "Fascia_eta": "Più di 65",
    "Sesso": "Donna",
    "Occupazione": "Pensionato/a",
    "Anni_Bologna": "Sono nato/a e cresciuto/a qui",
    "Dove_cresciuto": "Bologna (o provincia)",
    "Quartiere_Bologna": "Bolognina",
    "Titolo_studio": "Laurea magistrale o superiore",
    "Commento": "Era la mia sede di lavoro e non apprezzavo assolutamente le modalità di lavoro che erano state impostate dall'allora preside Tani"
  },
  {
    "ID": 164,
    "Luogo": "Via Antonio di Vincenzo",
    "Emozione": "Accettazione",
    "Fascia_eta": "Più di 65",
    "Sesso": "Donna",
    "Occupazione": "Pensionato/a",
    "Anni_Bologna": "Sono nato/a e cresciuto/a qui",
    "Dove_cresciuto": "Bologna (o provincia)",
    "Quartiere_Bologna": "Bolognina",
    "Titolo_studio": "Laurea magistrale o superiore",
    "Commento": "Le persone che lo frequentano, amici e compagni, nella sede di Coalizione Civica."
  },
  {
    "ID": 165,
    "Luogo": "Piazza Lucio Dalla",
    "Emozione": "Cambiamento",
    "Fascia_eta": "Più di 65",
    "Sesso": "Donna",
    "Occupazione": "Pensionato/a",
    "Anni_Bologna": "Sono nato/a e cresciuto/a qui",
    "Dove_cresciuto": "Bologna (o provincia)",
    "Quartiere_Bologna": "Bolognina",
    "Titolo_studio": "Laurea magistrale o superiore",
    "Commento": "Entrambe le cose. Il luogo è cambiato decisamente in meglio."
  },
  {
    "ID": 166,
    "Luogo": "Biblioteca Sala Borsa",
    "Emozione": "Felicità",
    "Fascia_eta": "Più di 65",
    "Sesso": "Donna",
    "Occupazione": "Pensionato/a",
    "Anni_Bologna": "Sono nato/a e cresciuto/a qui",
    "Dove_cresciuto": "Bologna (o provincia)",
    "Quartiere_Bologna": "Lame",
    "Titolo_studio": "Laurea magistrale o superiore",
    "Commento": "Da sempre. Ultimo l'incontro con ex colleghi dell'università"
  },
  {
    "ID": 167,
    "Luogo": "La Certosa",
    "Emozione": "Tristezza",
    "Fascia_eta": "Più di 65",
    "Sesso": "Donna",
    "Occupazione": "Pensionato/a",
    "Anni_Bologna": "Sono nato/a e cresciuto/a qui",
    "Dove_cresciuto": "Bologna (o provincia)",
    "Quartiere_Bologna": "Lame",
    "Titolo_studio": "Laurea magistrale o superiore",
    "Commento": "Ho visto tanti amici andarsene là."
  },
  {
    "ID": 168,
    "Luogo": "Bolognina",
    "Emozione": "Disagio",
    "Fascia_eta": "Più di 65",
    "Sesso": "Donna",
    "Occupazione": "Pensionato/a",
    "Anni_Bologna": "Sono nato/a e cresciuto/a qui",
    "Dove_cresciuto": "Bologna (o provincia)",
    "Quartiere_Bologna": "Lame",
    "Titolo_studio": "Laurea magistrale o superiore",
    "Commento": "È molto (e rapidamente) cambiata come popolazione e costumi, negozi, e altro ancora."
  },
  {
    "ID": 169,
    "Luogo": "Dipartimento di Lingue UNIBO",
    "Emozione": "Accettazione",
    "Fascia_eta": "Più di 65",
    "Sesso": "Donna",
    "Occupazione": "Pensionato/a",
    "Anni_Bologna": "Sono nato/a e cresciuto/a qui",
    "Dove_cresciuto": "Bologna (o provincia)",
    "Quartiere_Bologna": "Lame",
    "Titolo_studio": "Laurea magistrale o superiore",
    "Commento": "Ci ho vissuto molto tempo, ho avuto molte esperienze, ho avuto molti studenti che tuttora mi seguono."
  },
  {
    "ID": 170,
    "Luogo": "Stadio Dall'Ara",
    "Emozione": "Cambiamento",
    "Fascia_eta": "Più di 65",
    "Sesso": "Donna",
    "Occupazione": "Pensionato/a",
    "Anni_Bologna": "Sono nato/a e cresciuto/a qui",
    "Dove_cresciuto": "Bologna (o provincia)",
    "Quartiere_Bologna": "Lame",
    "Titolo_studio": "Laurea magistrale o superiore",
    "Commento": "Ci andavo da piccola con mio padre. Ora lo percepisco come un fastidio, un disordine alla circolazione delle auto"
  },
  {
    "ID": 171,
    "Luogo": "Parco della Montagnola",
    "Emozione": "Felicità",
    "Fascia_eta": "26-35",
    "Sesso": "Uomo",
    "Occupazione": "Occupato/a dipendente",
    "Anni_Bologna": "Ci vivo da più di 5 anni e non sono studente/ssa fuori sede",
    "Dove_cresciuto": "Altra città (o provincia) in Emilia Romagna",
    "Quartiere_Bologna": "Bolognina",
    "Titolo_studio": "Laurea magistrale o superiore",
    "Commento": "Nuovi incontri e nuove amicizie. Inizio percorso universitario"
  },
  {
    "ID": 172,
    "Luogo": "Stazione Centrale",
    "Emozione": "Disagio",
    "Fascia_eta": "26-35",
    "Sesso": "Uomo",
    "Occupazione": "Occupato/a dipendente",
    "Anni_Bologna": "Ci vivo da più di 5 anni e non sono studente/ssa fuori sede",
    "Dove_cresciuto": "Altra città (o provincia) in Emilia Romagna",
    "Quartiere_Bologna": "Bolognina",
    "Titolo_studio": "Laurea magistrale o superiore",
    "Commento": "POCA SICUREZZA E CAOS"
  },
  {
    "ID": 173,
    "Luogo": "Parco della Montagnola",
    "Emozione": "Accettazione",
    "Fascia_eta": "26-35",
    "Sesso": "Uomo",
    "Occupazione": "Occupato/a dipendente",
    "Anni_Bologna": "Ci vivo da più di 5 anni e non sono studente/ssa fuori sede",
    "Dove_cresciuto": "Altra città (o provincia) in Emilia Romagna",
    "Quartiere_Bologna": "Bolognina",
    "Titolo_studio": "Laurea magistrale o superiore",
    "Commento": "IL FATTO DI POTER ANDARCI COME VOGLIO SENZA ESSERE NOTATO COME DIVERSO"
  },
  {
    "ID": 174,
    "Luogo": "Bologna Centro",
    "Emozione": "Cambiamento",
    "Fascia_eta": "26-35",
    "Sesso": "Uomo",
    "Occupazione": "Occupato/a dipendente",
    "Anni_Bologna": "Ci vivo da più di 5 anni e non sono studente/ssa fuori sede",
    "Dove_cresciuto": "Altra città (o provincia) in Emilia Romagna",
    "Quartiere_Bologna": "Bolognina",
    "Titolo_studio": "Laurea magistrale o superiore",
    "Commento": "MI SEMBRA MENO FELICE LA GENTE CHE PASSEGGIA PER LA CITTÀ"
  },
  {
    "ID": 175,
    "Luogo": "Via Zamboni",
    "Emozione": "Felicità",
    "Fascia_eta": "56-65",
    "Sesso": "Donna",
    "Occupazione": "Pensionato/a",
    "Anni_Bologna": "Sono nato/a e cresciuto/a qui",
    "Dove_cresciuto": "Bologna (o provincia)",
    "Quartiere_Bologna": "Lame",
    "Titolo_studio": "Diploma di scuola superiore",
    "Commento": "Ci sono cresciuta"
  },
  {
    "ID": 176,
    "Luogo": "Ospedale Maggiore",
    "Emozione": "Tristezza",
    "Fascia_eta": "56-65",
    "Sesso": "Donna",
    "Occupazione": "Pensionato/a",
    "Anni_Bologna": "Sono nato/a e cresciuto/a qui",
    "Dove_cresciuto": "Bologna (o provincia)",
    "Quartiere_Bologna": "Lame",
    "Titolo_studio": "Diploma di scuola superiore",
    "Commento": "In ricoveri di mia mamma"
  },
  {
    "ID": 177,
    "Luogo": "Piazza VIII agosto",
    "Emozione": "Disagio",
    "Fascia_eta": "56-65",
    "Sesso": "Donna",
    "Occupazione": "Pensionato/a",
    "Anni_Bologna": "Sono nato/a e cresciuto/a qui",
    "Dove_cresciuto": "Bologna (o provincia)",
    "Quartiere_Bologna": "Lame",
    "Titolo_studio": "Diploma di scuola superiore",
    "Commento": "Non lo riconosco più come luogo di ritrovo"
  },
  {
    "ID": 178,
    "Luogo": "La Pescarola",
    "Emozione": "Accettazione",
    "Fascia_eta": "56-65",
    "Sesso": "Donna",
    "Occupazione": "Pensionato/a",
    "Anni_Bologna": "Sono nato/a e cresciuto/a qui",
    "Dove_cresciuto": "Bologna (o provincia)",
    "Quartiere_Bologna": "Lame",
    "Titolo_studio": "Diploma di scuola superiore",
    "Commento": "Adoro gli anziani del quartiere e i loro negozi di fiducia e il rapporto con i negozianti"
  },
  {
    "ID": 179,
    "Luogo": "Via Zamboni",
    "Emozione": "Cambiamento",
    "Fascia_eta": "56-65",
    "Sesso": "Donna",
    "Occupazione": "Pensionato/a",
    "Anni_Bologna": "Sono nato/a e cresciuto/a qui",
    "Dove_cresciuto": "Bologna (o provincia)",
    "Quartiere_Bologna": "Lame",
    "Titolo_studio": "Diploma di scuola superiore",
    "Commento": "La maleducazione della gente"
  },
  {
    "ID": 180,
    "Luogo": "Piazza Nettuno",
    "Emozione": "Felicità",
    "Fascia_eta": "56-65",
    "Sesso": "Donna",
    "Occupazione": "Occupato/a dipendente",
    "Anni_Bologna": "Sono nato/a e cresciuto/a qui",
    "Dove_cresciuto": "Bologna (o provincia)",
    "Quartiere_Bologna": "Corticella",
    "Titolo_studio": "Laurea magistrale o superiore",
    "Commento": "Partenza per un viaggio che mi ha cambiato la vita"
  },
  {
    "ID": 181,
    "Luogo": "Stazione Centrale",
    "Emozione": "Tristezza",
    "Fascia_eta": "56-65",
    "Sesso": "Donna",
    "Occupazione": "Occupato/a dipendente",
    "Anni_Bologna": "Sono nato/a e cresciuto/a qui",
    "Dove_cresciuto": "Bologna (o provincia)",
    "Quartiere_Bologna": "Corticella",
    "Titolo_studio": "Laurea magistrale o superiore",
    "Commento": "Strage 2 agosto"
  },
  {
    "ID": 182,
    "Luogo": "Chiesa di Via Genova",
    "Emozione": "Accettazione",
    "Fascia_eta": "56-65",
    "Sesso": "Donna",
    "Occupazione": "Occupato/a dipendente",
    "Anni_Bologna": "Sono nato/a e cresciuto/a qui",
    "Dove_cresciuto": "Bologna (o provincia)",
    "Quartiere_Bologna": "Corticella",
    "Titolo_studio": "Laurea magistrale o superiore",
    "Commento": "Infanzia passata lì"
  },
  {
    "ID": 183,
    "Luogo": "Scuole di Corticella",
    "Emozione": "Cambiamento",
    "Fascia_eta": "56-65",
    "Sesso": "Donna",
    "Occupazione": "Occupato/a dipendente",
    "Anni_Bologna": "Sono nato/a e cresciuto/a qui",
    "Dove_cresciuto": "Bologna (o provincia)",
    "Quartiere_Bologna": "Corticella",
    "Titolo_studio": "Laurea magistrale o superiore",
    "Commento": "Entrambe le cose"
  },
  {
    "ID": 184,
    "Luogo": "Giardini Del Laghetto di Corticella",
    "Emozione": "Felicità",
    "Fascia_eta": "46-55",
    "Sesso": "Uomo",
    "Occupazione": "Occupato/a dipendente",
    "Anni_Bologna": "Sono nato/a e cresciuto/a qui",
    "Dove_cresciuto": "Bologna (o provincia)",
    "Quartiere_Bologna": "Corticella",
    "Titolo_studio": "Diploma di scuola superiore",
    "Commento": "Era il nostro ritrovo estivo e ci giocavamo a calcio, tra fine anni '90 e metà anni 2000"
  },
  {
    "ID": 185,
    "Luogo": "Stazione Centrale",
    "Emozione": "Tristezza",
    "Fascia_eta": "46-55",
    "Sesso": "Uomo",
    "Occupazione": "Occupato/a dipendente",
    "Anni_Bologna": "Sono nato/a e cresciuto/a qui",
    "Dove_cresciuto": "Bologna (o provincia)",
    "Quartiere_Bologna": "Corticella",
    "Titolo_studio": "Diploma di scuola superiore",
    "Commento": "La strage del 1980, in cui avevo 6 anni"
  },
  {
    "ID": 186,
    "Luogo": "Parco della Montagnola",
    "Emozione": "Disagio",
    "Fascia_eta": "46-55",
    "Sesso": "Uomo",
    "Occupazione": "Occupato/a dipendente",
    "Anni_Bologna": "Sono nato/a e cresciuto/a qui",
    "Dove_cresciuto": "Bologna (o provincia)",
    "Quartiere_Bologna": "Corticella",
    "Titolo_studio": "Diploma di scuola superiore",
    "Commento": "Era sera e la sensazione di insicurezza era molto forte"
  },
  {
    "ID": 187,
    "Luogo": "Stadio Dall'Ara",
    "Emozione": "Accettazione",
    "Fascia_eta": "46-55",
    "Sesso": "Uomo",
    "Occupazione": "Occupato/a dipendente",
    "Anni_Bologna": "Sono nato/a e cresciuto/a qui",
    "Dove_cresciuto": "Bologna (o provincia)",
    "Quartiere_Bologna": "Corticella",
    "Titolo_studio": "Diploma di scuola superiore",
    "Commento": "Ci vado da quando avevo 7 anni e Mancini giocava nel Bologna"
  },
  {
    "ID": 188,
    "Luogo": "Centro Civico e Villa Torchi",
    "Emozione": "Cambiamento",
    "Fascia_eta": "46-55",
    "Sesso": "Uomo",
    "Occupazione": "Occupato/a dipendente",
    "Anni_Bologna": "Sono nato/a e cresciuto/a qui",
    "Dove_cresciuto": "Bologna (o provincia)",
    "Quartiere_Bologna": "Corticella",
    "Titolo_studio": "Diploma di scuola superiore",
    "Commento": "C'era una scuola elementare, un parco poco attrezzato e un campo da calcio regolamentare. Ora è abbastanza cambiato"
  },
  {
    "ID": 189,
    "Luogo": "Giardini Margherita",
    "Emozione": "Felicità",
    "Fascia_eta": "26-35",
    "Sesso": "Donna",
    "Occupazione": "Studente/ssa",
    "Anni_Bologna": "Sono studente/ssa fuori sede",
    "Dove_cresciuto": "Altra città (o provincia) in Italia",
    "Quartiere_Bologna": "Bolognina",
    "Titolo_studio": "Laurea triennale",
    "Commento": "Spazio verde molto amato"
  },
  {
    "ID": 190,
    "Luogo": "Piazza Lucio Dalla",
    "Emozione": "Felicità",
    "Fascia_eta": "26-35",
    "Sesso": "Donna",
    "Occupazione": "Studente/ssa",
    "Anni_Bologna": "Sono studente/ssa fuori sede",
    "Dove_cresciuto": "Altra città (o provincia) in Italia",
    "Quartiere_Bologna": "Bolognina",
    "Titolo_studio": "Laurea triennale",
    "Commento": "Per il mercatino del Senza chiedere permesso e varie assemblee e presentazioni"
  },
  {
    "ID": 191,
    "Luogo": "Giardino Guido Rossa",
    "Emozione": "Felicità",
    "Fascia_eta": "26-35",
    "Sesso": "Donna",
    "Occupazione": "Studente/ssa",
    "Anni_Bologna": "Sono studente/ssa fuori sede",
    "Dove_cresciuto": "Altra città (o provincia) in Italia",
    "Quartiere_Bologna": "Bolognina",
    "Titolo_studio": "Laurea triennale",
    "Commento": "Per le assemblee organizzate per fare una controproposta al comune in modo da rendere quello spazio pubblico e sociale anziché l'ennesimo parcheggio/centro commerciale"
  },
  {
    "ID": 192,
    "Luogo": "Centro Civico e Villa Torchi",
    "Emozione": "Felicità",
    "Fascia_eta": "36-45",
    "Sesso": "Donna",
    "Occupazione": "Occupato/a dipendente",
    "Anni_Bologna": "Sono nato/a e cresciuto/a qui",
    "Dove_cresciuto": "Bologna (o provincia)",
    "Quartiere_Bologna": "Corticella",
    "Titolo_studio": "Diploma di scuola superiore",
    "Commento": "Vissuto la mia adolescenza tra muretti e panchine"
  },
  {
    "ID": 193,
    "Luogo": "Via Malvasia",
    "Emozione": "Disagio",
    "Fascia_eta": "26-35",
    "Sesso": "Donna",
    "Occupazione": "Occupato/a dipendente",
    "Anni_Bologna": "Ci vivo da più di 5 anni e non sono studente/ssa fuori sede",
    "Dove_cresciuto": "Altra città (o provincia) in Italia",
    "Quartiere_Bologna": "Bolognina",
    "Titolo_studio": "Laurea magistrale o superiore",
    "Commento": "Provo questa sensazione ogni volta che ci passo di sera, mi sembra di essere seguita... O che posso perdermi tra quelle vie senza mai essere ritrovata"
  }
]
